{
"meta":{"test_sets":[],"test_metrics":[],"learn_metrics":[{"best_value":"Min","name":"RMSE"}],"launch_mode":"Train","parameters":"","iteration_count":1000,"learn_sets":["learn"],"name":"experiment"},
"iterations":[
{"learn":[14.4906349],"iteration":0,"passed_time":0.05215322247,"remaining_time":52.10106925},
{"learn":[14.119272],"iteration":1,"passed_time":0.05395896352,"remaining_time":26.9255228},
{"learn":[13.75138561],"iteration":2,"passed_time":0.05578968335,"remaining_time":18.54077143},
{"learn":[13.39313646],"iteration":3,"passed_time":0.05743048893,"remaining_time":14.30019174},
{"learn":[13.06647061],"iteration":4,"passed_time":0.05978961821,"remaining_time":11.89813402},
{"learn":[12.76264673],"iteration":5,"passed_time":0.06199889204,"remaining_time":10.27114978},
{"learn":[12.46731322],"iteration":6,"passed_time":0.06301383598,"remaining_time":8.938962732},
{"learn":[12.19890252],"iteration":7,"passed_time":0.0639830643,"remaining_time":7.933899974},
{"learn":[11.91891714],"iteration":8,"passed_time":0.0656941775,"remaining_time":7.233658878},
{"learn":[11.63652235],"iteration":9,"passed_time":0.06855261689,"remaining_time":6.786709072},
{"learn":[11.37002647],"iteration":10,"passed_time":0.0694673613,"remaining_time":6.245747302},
{"learn":[11.13822341],"iteration":11,"passed_time":0.07037253215,"remaining_time":5.794005147},
{"learn":[10.92623775],"iteration":12,"passed_time":0.07135851353,"remaining_time":5.417757912},
{"learn":[10.68738206],"iteration":13,"passed_time":0.07231705957,"remaining_time":5.093187196},
{"learn":[10.46165115],"iteration":14,"passed_time":0.0732270865,"remaining_time":4.80857868},
{"learn":[10.22945255],"iteration":15,"passed_time":0.07428396971,"remaining_time":4.568464137},
{"learn":[10.02198567],"iteration":16,"passed_time":0.07614304972,"remaining_time":4.402859875},
{"learn":[9.825726677],"iteration":17,"passed_time":0.07716798572,"remaining_time":4.209942332},
{"learn":[9.622598102],"iteration":18,"passed_time":0.07793821175,"remaining_time":4.024072933},
{"learn":[9.430722335],"iteration":19,"passed_time":0.07912892109,"remaining_time":3.877317133},
{"learn":[9.26121616],"iteration":20,"passed_time":0.08027530887,"remaining_time":3.742358447},
{"learn":[9.105994005],"iteration":21,"passed_time":0.08183439266,"remaining_time":3.637910728},
{"learn":[8.931332901],"iteration":22,"passed_time":0.08254709848,"remaining_time":3.506457183},
{"learn":[8.764631524],"iteration":23,"passed_time":0.08325407502,"remaining_time":3.385665717},
{"learn":[8.602864494],"iteration":24,"passed_time":0.08421725612,"remaining_time":3.284472989},
{"learn":[8.465981328],"iteration":25,"passed_time":0.08498066226,"remaining_time":3.183506348},
{"learn":[8.322314659],"iteration":26,"passed_time":0.08568503096,"remaining_time":3.087834634},
{"learn":[8.189202561],"iteration":27,"passed_time":0.08645354409,"remaining_time":3.001173031},
{"learn":[8.059828382],"iteration":28,"passed_time":0.08715470439,"remaining_time":2.91817993},
{"learn":[7.94656803],"iteration":29,"passed_time":0.08815536633,"remaining_time":2.850356845},
{"learn":[7.842441672],"iteration":30,"passed_time":0.0889069706,"remaining_time":2.779059823},
{"learn":[7.723190774],"iteration":31,"passed_time":0.089768213,"remaining_time":2.715488443},
{"learn":[7.62263374],"iteration":32,"passed_time":0.09051464235,"remaining_time":2.652353308},
{"learn":[7.522469748],"iteration":33,"passed_time":0.091255231,"remaining_time":2.592722151},
{"learn":[7.421088394],"iteration":34,"passed_time":0.09198332391,"remaining_time":2.536111645},
{"learn":[7.33039119],"iteration":35,"passed_time":0.09271830465,"remaining_time":2.482790158},
{"learn":[7.242480375],"iteration":36,"passed_time":0.09370859591,"remaining_time":2.438956158},
{"learn":[7.162150888],"iteration":37,"passed_time":0.0944493467,"remaining_time":2.391059777},
{"learn":[7.081011687],"iteration":38,"passed_time":0.09514753139,"remaining_time":2.344532761},
{"learn":[7.003100883],"iteration":39,"passed_time":0.09587198293,"remaining_time":2.30092759},
{"learn":[6.935495298],"iteration":40,"passed_time":0.09658998505,"remaining_time":2.259263309},
{"learn":[6.879812269],"iteration":41,"passed_time":0.09731671019,"remaining_time":2.219747818},
{"learn":[6.809053695],"iteration":42,"passed_time":0.09804763197,"remaining_time":2.182129856},
{"learn":[6.749556],"iteration":43,"passed_time":0.09871575535,"remaining_time":2.144824139},
{"learn":[6.686851869],"iteration":44,"passed_time":0.09940512736,"remaining_time":2.109597703},
{"learn":[6.624374083],"iteration":45,"passed_time":0.1001246802,"remaining_time":2.076498803},
{"learn":[6.569390432],"iteration":46,"passed_time":0.1008474144,"remaining_time":2.044842253},
{"learn":[6.512260834],"iteration":47,"passed_time":0.1029747227,"remaining_time":2.042332001},
{"learn":[6.456276091],"iteration":48,"passed_time":0.1037404487,"remaining_time":2.013411565},
{"learn":[6.408337838],"iteration":49,"passed_time":0.1044577234,"remaining_time":1.984696745},
{"learn":[6.363060498],"iteration":50,"passed_time":0.1051848127,"remaining_time":1.957262495},
{"learn":[6.320559683],"iteration":51,"passed_time":0.1059129754,"remaining_time":1.930875012},
{"learn":[6.27735835],"iteration":52,"passed_time":0.1065696429,"remaining_time":1.904178336},
{"learn":[6.229136326],"iteration":53,"passed_time":0.1074331036,"remaining_time":1.882068816},
{"learn":[6.185930613],"iteration":54,"passed_time":0.1081262149,"remaining_time":1.857804964},
{"learn":[6.148133778],"iteration":55,"passed_time":0.1088815946,"remaining_time":1.835432594},
{"learn":[6.11287649],"iteration":56,"passed_time":0.109602883,"remaining_time":1.813254713},
{"learn":[6.07919906],"iteration":57,"passed_time":0.1103195681,"remaining_time":1.79174195},
{"learn":[6.04559752],"iteration":58,"passed_time":0.1110292784,"remaining_time":1.770822897},
{"learn":[6.013690246],"iteration":59,"passed_time":0.1117476899,"remaining_time":1.750713809},
{"learn":[5.982979263],"iteration":60,"passed_time":0.1124589274,"remaining_time":1.731130047},
{"learn":[5.952349508],"iteration":61,"passed_time":0.1132534375,"remaining_time":1.713414909},
{"learn":[5.916903326],"iteration":62,"passed_time":0.1140139622,"remaining_time":1.69573147},
{"learn":[5.882308401],"iteration":63,"passed_time":0.1147074448,"remaining_time":1.67759638},
{"learn":[5.854369062],"iteration":64,"passed_time":0.1154365341,"remaining_time":1.660510145},
{"learn":[5.826143061],"iteration":65,"passed_time":0.1171293924,"remaining_time":1.657558371},
{"learn":[5.802255359],"iteration":66,"passed_time":0.1180703149,"remaining_time":1.644173191},
{"learn":[5.774273956],"iteration":67,"passed_time":0.1188975131,"remaining_time":1.629595327},
{"learn":[5.756912427],"iteration":68,"passed_time":0.1195570131,"remaining_time":1.613153322},
{"learn":[5.732781638],"iteration":69,"passed_time":0.1203131537,"remaining_time":1.598446185},
{"learn":[5.711686686],"iteration":70,"passed_time":0.1210146247,"remaining_time":1.583416709},
{"learn":[5.689172344],"iteration":71,"passed_time":0.1219184441,"remaining_time":1.571393279},
{"learn":[5.671261979],"iteration":72,"passed_time":0.1226363149,"remaining_time":1.557313204},
{"learn":[5.652425881],"iteration":73,"passed_time":0.123309297,"remaining_time":1.543032555},
{"learn":[5.632919076],"iteration":74,"passed_time":0.1240671542,"remaining_time":1.530161568},
{"learn":[5.611213563],"iteration":75,"passed_time":0.1247972444,"remaining_time":1.517271761},
{"learn":[5.594770719],"iteration":76,"passed_time":0.1254903402,"remaining_time":1.504254338},
{"learn":[5.57978765],"iteration":77,"passed_time":0.1262088704,"remaining_time":1.491853571},
{"learn":[5.566841169],"iteration":78,"passed_time":0.1269713146,"remaining_time":1.480260516},
{"learn":[5.549888213],"iteration":79,"passed_time":0.1277236526,"remaining_time":1.468822005},
{"learn":[5.538484105],"iteration":80,"passed_time":0.128154589,"remaining_time":1.454000831},
{"learn":[5.519950256],"iteration":81,"passed_time":0.1289333424,"remaining_time":1.443424492},
{"learn":[5.505351592],"iteration":82,"passed_time":0.1309821356,"remaining_time":1.447115883},
{"learn":[5.48919068],"iteration":83,"passed_time":0.1317634542,"remaining_time":1.436849096},
{"learn":[5.477247218],"iteration":84,"passed_time":0.132546849,"remaining_time":1.426827845},
{"learn":[5.461079554],"iteration":85,"passed_time":0.1333909697,"remaining_time":1.417666817},
{"learn":[5.449118235],"iteration":86,"passed_time":0.1341149139,"remaining_time":1.407435821},
{"learn":[5.437074272],"iteration":87,"passed_time":0.1349301554,"remaining_time":1.398367065},
{"learn":[5.423661881],"iteration":88,"passed_time":0.136020225,"remaining_time":1.39229691},
{"learn":[5.410450686],"iteration":89,"passed_time":0.1367322732,"remaining_time":1.382515207},
{"learn":[5.402336844],"iteration":90,"passed_time":0.1373637744,"remaining_time":1.372128252},
{"learn":[5.392839264],"iteration":91,"passed_time":0.1380489253,"remaining_time":1.362482872},
{"learn":[5.383193727],"iteration":92,"passed_time":0.138765018,"remaining_time":1.35333195},
{"learn":[5.375852504],"iteration":93,"passed_time":0.1394780255,"remaining_time":1.344330756},
{"learn":[5.365893033],"iteration":94,"passed_time":0.1402238099,"remaining_time":1.335816294},
{"learn":[5.353654397],"iteration":95,"passed_time":0.1409138187,"remaining_time":1.326938459},
{"learn":[5.342020991],"iteration":96,"passed_time":0.1416747673,"remaining_time":1.318889844},
{"learn":[5.333801959],"iteration":97,"passed_time":0.1423640116,"remaining_time":1.310329985},
{"learn":[5.325791094],"iteration":98,"passed_time":0.1430868399,"remaining_time":1.302234776},
{"learn":[5.319631851],"iteration":99,"passed_time":0.1447485074,"remaining_time":1.302736566},
{"learn":[5.305572917],"iteration":100,"passed_time":0.1465404039,"remaining_time":1.304354685},
{"learn":[5.295416635],"iteration":101,"passed_time":0.1472933995,"remaining_time":1.296759537},
{"learn":[5.2874148],"iteration":102,"passed_time":0.1480346567,"remaining_time":1.28919502},
{"learn":[5.276230574],"iteration":103,"passed_time":0.1487709056,"remaining_time":1.281718571},
{"learn":[5.266541539],"iteration":104,"passed_time":0.1494963798,"remaining_time":1.274278666},
{"learn":[5.25829393],"iteration":105,"passed_time":0.1504393729,"remaining_time":1.268799994},
{"learn":[5.24934963],"iteration":106,"passed_time":0.1511605228,"remaining_time":1.261554643},
{"learn":[5.241981306],"iteration":107,"passed_time":0.1518481022,"remaining_time":1.254152844},
{"learn":[5.233106042],"iteration":108,"passed_time":0.1525267828,"remaining_time":1.2468015},
{"learn":[5.226514888],"iteration":109,"passed_time":0.1532619366,"remaining_time":1.240028396},
{"learn":[5.223613248],"iteration":110,"passed_time":0.1537071052,"remaining_time":1.23104159},
{"learn":[5.214076666],"iteration":111,"passed_time":0.1544221978,"remaining_time":1.224347426},
{"learn":[5.206705974],"iteration":112,"passed_time":0.1551504801,"remaining_time":1.217862618},
{"learn":[5.200666367],"iteration":113,"passed_time":0.1558324851,"remaining_time":1.211119139},
{"learn":[5.194906285],"iteration":114,"passed_time":0.156532649,"remaining_time":1.20462082},
{"learn":[5.190251648],"iteration":115,"passed_time":0.1572811979,"remaining_time":1.198591198},
{"learn":[5.185562784],"iteration":116,"passed_time":0.1579715718,"remaining_time":1.192212802},
{"learn":[5.179879481],"iteration":117,"passed_time":0.1600866317,"remaining_time":1.196579739},
{"learn":[5.178164798],"iteration":118,"passed_time":0.1606173736,"remaining_time":1.189108455},
{"learn":[5.168936709],"iteration":119,"passed_time":0.1613962647,"remaining_time":1.183572608},
{"learn":[5.16371573],"iteration":120,"passed_time":0.1622399379,"remaining_time":1.178585995},
{"learn":[5.159783658],"iteration":121,"passed_time":0.1628548437,"remaining_time":1.172020924},
{"learn":[5.153689975],"iteration":122,"passed_time":0.1639338795,"remaining_time":1.168861889},
{"learn":[5.146879452],"iteration":123,"passed_time":0.1663399518,"remaining_time":1.175111273},
{"learn":[5.141649518],"iteration":124,"passed_time":0.167322954,"remaining_time":1.171260678},
{"learn":[5.135916084],"iteration":125,"passed_time":0.16830163,"remaining_time":1.167425592},
{"learn":[5.127723422],"iteration":126,"passed_time":0.1693300081,"remaining_time":1.163977142},
{"learn":[5.122669937],"iteration":127,"passed_time":0.1702831265,"remaining_time":1.160053799},
{"learn":[5.116483159],"iteration":128,"passed_time":0.1712733806,"remaining_time":1.156427244},
{"learn":[5.110227433],"iteration":129,"passed_time":0.1721862807,"remaining_time":1.152323571},
{"learn":[5.101119295],"iteration":130,"passed_time":0.1729220187,"remaining_time":1.147093392},
{"learn":[5.096973722],"iteration":131,"passed_time":0.1740270714,"remaining_time":1.144359833},
{"learn":[5.091908274],"iteration":132,"passed_time":0.1747466859,"remaining_time":1.139138171},
{"learn":[5.083595931],"iteration":133,"passed_time":0.1754918752,"remaining_time":1.134148984},
{"learn":[5.079052718],"iteration":134,"passed_time":0.1763254476,"remaining_time":1.129788979},
{"learn":[5.071858282],"iteration":135,"passed_time":0.1771138914,"remaining_time":1.125194134},
{"learn":[5.067309697],"iteration":136,"passed_time":0.1778804462,"remaining_time":1.120516971},
{"learn":[5.064577813],"iteration":137,"passed_time":0.1786392753,"remaining_time":1.115848227},
{"learn":[5.060447488],"iteration":138,"passed_time":0.1793454212,"remaining_time":1.110909407},
{"learn":[5.054881425],"iteration":139,"passed_time":0.180044162,"remaining_time":1.105985567},
{"learn":[5.050888147],"iteration":140,"passed_time":0.1810651441,"remaining_time":1.103084814},
{"learn":[5.048181897],"iteration":141,"passed_time":0.181875159,"remaining_time":1.09893582},
{"learn":[5.047159265],"iteration":142,"passed_time":0.1823217516,"remaining_time":1.092655532},
{"learn":[5.042375049],"iteration":143,"passed_time":0.1830782319,"remaining_time":1.088298378},
{"learn":[5.038126541],"iteration":144,"passed_time":0.1839767857,"remaining_time":1.084828633},
{"learn":[5.031164921],"iteration":145,"passed_time":0.1848929604,"remaining_time":1.081497179},
{"learn":[5.024111501],"iteration":146,"passed_time":0.1857404969,"remaining_time":1.077800298},
{"learn":[5.021062136],"iteration":147,"passed_time":0.1866381504,"remaining_time":1.074430433},
{"learn":[5.017292019],"iteration":148,"passed_time":0.1875423864,"remaining_time":1.071131348},
{"learn":[5.016404506],"iteration":149,"passed_time":0.187929774,"remaining_time":1.064935386},
{"learn":[5.013697351],"iteration":150,"passed_time":0.1889950015,"remaining_time":1.062627525},
{"learn":[5.009923666],"iteration":151,"passed_time":0.1898393659,"remaining_time":1.059103831},
{"learn":[5.005399351],"iteration":152,"passed_time":0.1915518885,"remaining_time":1.060421239},
{"learn":[5.00046183],"iteration":153,"passed_time":0.1922251732,"remaining_time":1.055990237},
{"learn":[4.999441782],"iteration":154,"passed_time":0.1928828064,"remaining_time":1.051522396},
{"learn":[4.995363341],"iteration":155,"passed_time":0.1936113848,"remaining_time":1.047487236},
{"learn":[4.990330624],"iteration":156,"passed_time":0.1943408881,"remaining_time":1.043499163},
{"learn":[4.983435485],"iteration":157,"passed_time":0.1950093267,"remaining_time":1.039226918},
{"learn":[4.974335721],"iteration":158,"passed_time":0.1956440608,"remaining_time":1.03482173},
{"learn":[4.969928714],"iteration":159,"passed_time":0.1963349727,"remaining_time":1.030758607},
{"learn":[4.965776322],"iteration":160,"passed_time":0.1970296184,"remaining_time":1.026756831},
{"learn":[4.960269856],"iteration":161,"passed_time":0.1976939853,"remaining_time":1.022639257},
{"learn":[4.956467935],"iteration":162,"passed_time":0.1983542335,"remaining_time":1.018542905},
{"learn":[4.952073352],"iteration":163,"passed_time":0.1990195978,"remaining_time":1.014514535},
{"learn":[4.950862645],"iteration":164,"passed_time":0.1993475113,"remaining_time":1.008819224},
{"learn":[4.946662382],"iteration":165,"passed_time":0.1999870915,"remaining_time":1.004754424},
{"learn":[4.941217419],"iteration":166,"passed_time":0.2006044104,"remaining_time":1.000619604},
{"learn":[4.94046833],"iteration":167,"passed_time":0.2009406691,"remaining_time":0.9951347424},
{"learn":[4.937503488],"iteration":168,"passed_time":0.2019285247,"remaining_time":0.9929148165},
{"learn":[4.935729415],"iteration":169,"passed_time":0.2025831604,"remaining_time":0.9890824892},
{"learn":[4.931924042],"iteration":170,"passed_time":0.2032306031,"remaining_time":0.9852524562},
{"learn":[4.929715847],"iteration":171,"passed_time":0.2038628136,"remaining_time":0.9813861029},
{"learn":[4.924063612],"iteration":172,"passed_time":0.2045119665,"remaining_time":0.977638129},
{"learn":[4.919994784],"iteration":173,"passed_time":0.2051746043,"remaining_time":0.9739897882},
{"learn":[4.917459782],"iteration":174,"passed_time":0.205874424,"remaining_time":0.9705508559},
{"learn":[4.912927241],"iteration":175,"passed_time":0.206573009,"remaining_time":0.9671372696},
{"learn":[4.906348922],"iteration":176,"passed_time":0.2072979751,"remaining_time":0.9638770254},
{"learn":[4.904446547],"iteration":177,"passed_time":0.207968825,"remaining_time":0.9603953602},
{"learn":[4.898042686],"iteration":178,"passed_time":0.2085967211,"remaining_time":0.9567480894},
{"learn":[4.897547428],"iteration":179,"passed_time":0.2089296817,"remaining_time":0.9517907724},
{"learn":[4.893458024],"iteration":180,"passed_time":0.2095760384,"remaining_time":0.9483026267},
{"learn":[4.89001205],"iteration":181,"passed_time":0.2102311905,"remaining_time":0.9448852407},
{"learn":[4.885690598],"iteration":182,"passed_time":0.2109564645,"remaining_time":0.941811101},
{"learn":[4.882155256],"iteration":183,"passed_time":0.2116252826,"remaining_time":0.938512123},
{"learn":[4.877888255],"iteration":184,"passed_time":0.2122720279,"remaining_time":0.9351443389},
{"learn":[4.874396759],"iteration":185,"passed_time":0.2129648266,"remaining_time":0.9320073593},
{"learn":[4.866303141],"iteration":186,"passed_time":0.2136071061,"remaining_time":0.9286768838},
{"learn":[4.864851831],"iteration":187,"passed_time":0.2142195599,"remaining_time":0.9252461841},
{"learn":[4.862512442],"iteration":188,"passed_time":0.2149514599,"remaining_time":0.9223578519},
{"learn":[4.857148912],"iteration":189,"passed_time":0.2156543703,"remaining_time":0.9193686311},
{"learn":[4.85298049],"iteration":190,"passed_time":0.2163909543,"remaining_time":0.9165459792},
{"learn":[4.849245415],"iteration":191,"passed_time":0.2170885058,"remaining_time":0.9135807954},
{"learn":[4.845000954],"iteration":192,"passed_time":0.2177619862,"remaining_time":0.9105384604},
{"learn":[4.84372628],"iteration":193,"passed_time":0.218384865,"remaining_time":0.9073103154},
{"learn":[4.839073037],"iteration":194,"passed_time":0.2190108525,"remaining_time":0.9041217246},
{"learn":[4.837740694],"iteration":195,"passed_time":0.2196435739,"remaining_time":0.9009869053},
{"learn":[4.832654407],"iteration":196,"passed_time":0.2203454824,"remaining_time":0.8981595045},
{"learn":[4.830387363],"iteration":197,"passed_time":0.2210447161,"remaining_time":0.8953427388},
{"learn":[4.828532161],"iteration":198,"passed_time":0.2216790344,"remaining_time":0.8922859625},
{"learn":[4.827232047],"iteration":199,"passed_time":0.2223228303,"remaining_time":0.8892913211},
{"learn":[4.823030909],"iteration":200,"passed_time":0.222983968,"remaining_time":0.8863890072},
{"learn":[4.819915068],"iteration":201,"passed_time":0.2236287648,"remaining_time":0.8834443284},
{"learn":[4.813511822],"iteration":202,"passed_time":0.2242780019,"remaining_time":0.8805397416},
{"learn":[4.810993123],"iteration":203,"passed_time":0.2249294121,"remaining_time":0.8776657453},
{"learn":[4.807434853],"iteration":204,"passed_time":0.2255942202,"remaining_time":0.8748653906},
{"learn":[4.804490986],"iteration":205,"passed_time":0.2262593789,"remaining_time":0.8720871205},
{"learn":[4.80182016],"iteration":206,"passed_time":0.2268898756,"remaining_time":0.8691964798},
{"learn":[4.799336783],"iteration":207,"passed_time":0.2274911724,"remaining_time":0.8662163872},
{"learn":[4.794227965],"iteration":208,"passed_time":0.2281375743,"remaining_time":0.8634297669},
{"learn":[4.790829337],"iteration":209,"passed_time":0.2310007919,"remaining_time":0.869002979},
{"learn":[4.784469441],"iteration":210,"passed_time":0.2317669644,"remaining_time":0.8666546678},
{"learn":[4.782601073],"iteration":211,"passed_time":0.2324461007,"remaining_time":0.8639977704},
{"learn":[4.778530305],"iteration":212,"passed_time":0.2331521786,"remaining_time":0.8614589887},
{"learn":[4.773718358],"iteration":213,"passed_time":0.2338536007,"remaining_time":0.8589202344},
{"learn":[4.770552572],"iteration":214,"passed_time":0.2345724833,"remaining_time":0.8564623228},
{"learn":[4.765534653],"iteration":215,"passed_time":0.2352925045,"remaining_time":0.854024646},
{"learn":[4.76287436],"iteration":216,"passed_time":0.2360216029,"remaining_time":0.8516355532},
{"learn":[4.75901552],"iteration":217,"passed_time":0.236823643,"remaining_time":0.8495233431},
{"learn":[4.753941536],"iteration":218,"passed_time":0.2375618149,"remaining_time":0.8471953307},
{"learn":[4.750449945],"iteration":219,"passed_time":0.2382630658,"remaining_time":0.8447508695},
{"learn":[4.748350367],"iteration":220,"passed_time":0.2389213547,"remaining_time":0.842170748},
{"learn":[4.743098282],"iteration":221,"passed_time":0.2396445499,"remaining_time":0.8398354045},
{"learn":[4.739834545],"iteration":222,"passed_time":0.2403415389,"remaining_time":0.8374232095},
{"learn":[4.737406347],"iteration":223,"passed_time":0.2410568272,"remaining_time":0.8350897228},
{"learn":[4.735588691],"iteration":224,"passed_time":0.2418094215,"remaining_time":0.8328991186},
{"learn":[4.73467813],"iteration":225,"passed_time":0.2425135746,"remaining_time":0.8305553397},
{"learn":[4.732230294],"iteration":226,"passed_time":0.243226179,"remaining_time":0.8282547858},
{"learn":[4.726154194],"iteration":227,"passed_time":0.2439158391,"remaining_time":0.8258904726},
{"learn":[4.722951687],"iteration":228,"passed_time":0.2446139875,"remaining_time":0.8235693641},
{"learn":[4.720333292],"iteration":229,"passed_time":0.2453155346,"remaining_time":0.8212737463},
{"learn":[4.717957451],"iteration":230,"passed_time":0.2460391791,"remaining_time":0.8190654922},
{"learn":[4.715468108],"iteration":231,"passed_time":0.246854791,"remaining_time":0.8171744805},
{"learn":[4.712485055],"iteration":232,"passed_time":0.2475495888,"remaining_time":0.8148949984},
{"learn":[4.70921509],"iteration":233,"passed_time":0.2482409256,"remaining_time":0.8126177307},
{"learn":[4.708203952],"iteration":234,"passed_time":0.2489469311,"remaining_time":0.8104017118},
{"learn":[4.702554715],"iteration":235,"passed_time":0.2498499497,"remaining_time":0.8088362778},
{"learn":[4.700363757],"iteration":236,"passed_time":0.2507185002,"remaining_time":0.8071654669},
{"learn":[4.69554337],"iteration":237,"passed_time":0.2517746615,"remaining_time":0.8061020675},
{"learn":[4.693785534],"iteration":238,"passed_time":0.2524732764,"remaining_time":0.8039002652},
{"learn":[4.68875529],"iteration":239,"passed_time":0.2534899134,"remaining_time":0.802718059},
{"learn":[4.682041788],"iteration":240,"passed_time":0.2542442677,"remaining_time":0.8007111999},
{"learn":[4.67958563],"iteration":241,"passed_time":0.2549375709,"remaining_time":0.798523466},
{"learn":[4.678247071],"iteration":242,"passed_time":0.255700122,"remaining_time":0.7965637545},
{"learn":[4.673895819],"iteration":243,"passed_time":0.2563814839,"remaining_time":0.7943623025},
{"learn":[4.666354853],"iteration":244,"passed_time":0.2570892738,"remaining_time":0.792254701},
{"learn":[4.661668097],"iteration":245,"passed_time":0.2578221712,"remaining_time":0.7902354353},
{"learn":[4.657647577],"iteration":246,"passed_time":0.2585160596,"remaining_time":0.7881076635},
{"learn":[4.652464954],"iteration":247,"passed_time":0.2593506982,"remaining_time":0.7864182461},
{"learn":[4.648642334],"iteration":248,"passed_time":0.2600577191,"remaining_time":0.7843507914},
{"learn":[4.6438327],"iteration":249,"passed_time":0.2607238995,"remaining_time":0.7821716986},
{"learn":[4.641666499],"iteration":250,"passed_time":0.2616873424,"remaining_time":0.780891711},
{"learn":[4.640967665],"iteration":251,"passed_time":0.2624322554,"remaining_time":0.7789655835},
{"learn":[4.639258081],"iteration":252,"passed_time":0.263248361,"remaining_time":0.7772589948},
{"learn":[4.636661682],"iteration":253,"passed_time":0.2639821479,"remaining_time":0.775317647},
{"learn":[4.631497689],"iteration":254,"passed_time":0.2646964027,"remaining_time":0.7733287058},
{"learn":[4.63007801],"iteration":255,"passed_time":0.2653653893,"remaining_time":0.7712181626},
{"learn":[4.627747039],"iteration":256,"passed_time":0.2661366353,"remaining_time":0.7694144747},
{"learn":[4.625773846],"iteration":257,"passed_time":0.2668207073,"remaining_time":0.7673680808},
{"learn":[4.624172715],"iteration":258,"passed_time":0.2675433282,"remaining_time":0.765442495},
{"learn":[4.621533025],"iteration":259,"passed_time":0.2682405111,"remaining_time":0.7634537623},
{"learn":[4.615482902],"iteration":260,"passed_time":0.2689716439,"remaining_time":0.7615710531},
{"learn":[4.612979212],"iteration":261,"passed_time":0.2696684119,"remaining_time":0.7596003359},
{"learn":[4.609827711],"iteration":262,"passed_time":0.270375931,"remaining_time":0.7576694341},
{"learn":[4.605681827],"iteration":263,"passed_time":0.2714846831,"remaining_time":0.7568663892},
{"learn":[4.601934387],"iteration":264,"passed_time":0.2721464078,"remaining_time":0.7548211687},
{"learn":[4.596579882],"iteration":265,"passed_time":0.2729351269,"remaining_time":0.7531367789},
{"learn":[4.595037606],"iteration":266,"passed_time":0.2737010377,"remaining_time":0.7513964817},
{"learn":[4.591547366],"iteration":267,"passed_time":0.2744339015,"remaining_time":0.7495731937},
{"learn":[4.588878588],"iteration":268,"passed_time":0.2751133132,"remaining_time":0.7476127581},
{"learn":[4.585416079],"iteration":269,"passed_time":0.2758726549,"remaining_time":0.7458779189},
{"learn":[4.580586654],"iteration":270,"passed_time":0.2766741814,"remaining_time":0.7442637574},
{"learn":[4.576770116],"iteration":271,"passed_time":0.2776925231,"remaining_time":0.7432358706},
{"learn":[4.573583917],"iteration":272,"passed_time":0.2783836741,"remaining_time":0.7413367439},
{"learn":[4.568391931],"iteration":273,"passed_time":0.2791331397,"remaining_time":0.7396009469},
{"learn":[4.566064701],"iteration":274,"passed_time":0.2799105824,"remaining_time":0.7379460809},
{"learn":[4.56378066],"iteration":275,"passed_time":0.2806702928,"remaining_time":0.736251058},
{"learn":[4.562888203],"iteration":276,"passed_time":0.2814162493,"remaining_time":0.7345268891},
{"learn":[4.55939515],"iteration":277,"passed_time":0.2821510136,"remaining_time":0.73278069},
{"learn":[4.558005428],"iteration":278,"passed_time":0.2830124761,"remaining_time":0.7313691587},
{"learn":[4.556397241],"iteration":279,"passed_time":0.2837435564,"remaining_time":0.7296262879},
{"learn":[4.55349601],"iteration":280,"passed_time":0.2844622995,"remaining_time":0.727859051},
{"learn":[4.549396397],"iteration":281,"passed_time":0.2851773785,"remaining_time":0.7260899213},
{"learn":[4.54676099],"iteration":282,"passed_time":0.2859887775,"remaining_time":0.7245722738},
{"learn":[4.5435957],"iteration":283,"passed_time":0.2869630848,"remaining_time":0.7234703123},
{"learn":[4.541892645],"iteration":284,"passed_time":0.2879388984,"remaining_time":0.7223730257},
{"learn":[4.537515486],"iteration":285,"passed_time":0.2888971283,"remaining_time":0.7212326909},
{"learn":[4.535588554],"iteration":286,"passed_time":0.2896483956,"remaining_time":0.7195794636},
{"learn":[4.534193068],"iteration":287,"passed_time":0.2903881799,"remaining_time":0.7179041113},
{"learn":[4.529604417],"iteration":288,"passed_time":0.2911207285,"remaining_time":0.7162174324},
{"learn":[4.527232549],"iteration":289,"passed_time":0.291848585,"remaining_time":0.714525846},
{"learn":[4.525777848],"iteration":290,"passed_time":0.2926302551,"remaining_time":0.7129719961},
{"learn":[4.524911528],"iteration":291,"passed_time":0.2933993199,"remaining_time":0.7113928715},
{"learn":[4.518629031],"iteration":292,"passed_time":0.294218325,"remaining_time":0.7099397808},
{"learn":[4.516796732],"iteration":293,"passed_time":0.2949884777,"remaining_time":0.7083736912},
{"learn":[4.512993623],"iteration":294,"passed_time":0.2957297103,"remaining_time":0.706743884},
{"learn":[4.507112738],"iteration":295,"passed_time":0.2964858283,"remaining_time":0.7051554835},
{"learn":[4.504704512],"iteration":296,"passed_time":0.2972103387,"remaining_time":0.7034978724},
{"learn":[4.503026727],"iteration":297,"passed_time":0.297999287,"remaining_time":0.7019983205},
{"learn":[4.496016281],"iteration":298,"passed_time":0.2988093898,"remaining_time":0.7005531179},
{"learn":[4.491351783],"iteration":299,"passed_time":0.3021933708,"remaining_time":0.7051178653},
{"learn":[4.486759302],"iteration":300,"passed_time":0.3042913063,"remaining_time":0.7066432662},
{"learn":[4.484402588],"iteration":301,"passed_time":0.3049568481,"remaining_time":0.7048340397},
{"learn":[4.479504411],"iteration":302,"passed_time":0.3056488407,"remaining_time":0.7030932077},
{"learn":[4.478828259],"iteration":303,"passed_time":0.3063229868,"remaining_time":0.7013184172},
{"learn":[4.474004593],"iteration":304,"passed_time":0.3069399579,"remaining_time":0.6994205597},
{"learn":[4.473159461],"iteration":305,"passed_time":0.3075647362,"remaining_time":0.6975487807},
{"learn":[4.467304759],"iteration":306,"passed_time":0.30820458,"remaining_time":0.6957191333},
{"learn":[4.465196553],"iteration":307,"passed_time":0.3088904872,"remaining_time":0.6940007051},
{"learn":[4.460857587],"iteration":308,"passed_time":0.3095579149,"remaining_time":0.692247635},
{"learn":[4.458428215],"iteration":309,"passed_time":0.3102794452,"remaining_time":0.690621991},
{"learn":[4.454709673],"iteration":310,"passed_time":0.310936139,"remaining_time":0.6888585202},
{"learn":[4.449531524],"iteration":311,"passed_time":0.3115496662,"remaining_time":0.6870069562},
{"learn":[4.448223089],"iteration":312,"passed_time":0.3123282167,"remaining_time":0.6855255107},
{"learn":[4.443456639],"iteration":313,"passed_time":0.3132974368,"remaining_time":0.6844651008},
{"learn":[4.439987712],"iteration":314,"passed_time":0.313926583,"remaining_time":0.6826657439},
{"learn":[4.435170329],"iteration":315,"passed_time":0.3145715111,"remaining_time":0.6809079544},
{"learn":[4.432417732],"iteration":316,"passed_time":0.3151947504,"remaining_time":0.6791104559},
{"learn":[4.427074214],"iteration":317,"passed_time":0.3158890528,"remaining_time":0.6774727484},
{"learn":[4.424773574],"iteration":318,"passed_time":0.3165710841,"remaining_time":0.6758147594},
{"learn":[4.419808728],"iteration":319,"passed_time":0.3171990644,"remaining_time":0.6740480119},
{"learn":[4.413974829],"iteration":320,"passed_time":0.3181162663,"remaining_time":0.6729001396},
{"learn":[4.411305423],"iteration":321,"passed_time":0.3188141358,"remaining_time":0.6712918759},
{"learn":[4.410264893],"iteration":322,"passed_time":0.3194974886,"remaining_time":0.6696588229},
{"learn":[4.40943868],"iteration":323,"passed_time":0.3201919685,"remaining_time":0.6680548479},
{"learn":[4.406876294],"iteration":324,"passed_time":0.3208817799,"remaining_time":0.6664467735},
{"learn":[4.404780237],"iteration":325,"passed_time":0.3215724173,"remaining_time":0.6648460407},
{"learn":[4.400686129],"iteration":326,"passed_time":0.322354235,"remaining_time":0.6634385327},
{"learn":[4.394692165],"iteration":327,"passed_time":0.3231334341,"remaining_time":0.6620294747},
{"learn":[4.393058864],"iteration":328,"passed_time":0.3238565441,"remaining_time":0.6605098514},
{"learn":[4.387164494],"iteration":329,"passed_time":0.3245585033,"remaining_time":0.6589521128},
{"learn":[4.384744462],"iteration":330,"passed_time":0.3252436298,"remaining_time":0.6573655237},
{"learn":[4.381874172],"iteration":331,"passed_time":0.3258989114,"remaining_time":0.6557243158},
{"learn":[4.376314041],"iteration":332,"passed_time":0.3268133922,"remaining_time":0.6546082061},
{"learn":[4.375146279],"iteration":333,"passed_time":0.3275744686,"remaining_time":0.6531874135},
{"learn":[4.37147413],"iteration":334,"passed_time":0.3282794741,"remaining_time":0.6516592546},
{"learn":[4.365860435],"iteration":335,"passed_time":0.3294810279,"remaining_time":0.6511172694},
{"learn":[4.362036028],"iteration":336,"passed_time":0.3301428115,"remaining_time":0.6495094481},
{"learn":[4.35895023],"iteration":337,"passed_time":0.3310191049,"remaining_time":0.6483273593},
{"learn":[4.357499309],"iteration":338,"passed_time":0.3320994632,"remaining_time":0.6475449711},
{"learn":[4.353327999],"iteration":339,"passed_time":0.3330067636,"remaining_time":0.6464248941},
{"learn":[4.352593014],"iteration":340,"passed_time":0.3351921928,"remaining_time":0.6477761145},
{"learn":[4.348275881],"iteration":341,"passed_time":0.3362090888,"remaining_time":0.6468584222},
{"learn":[4.343208675],"iteration":342,"passed_time":0.3372860621,"remaining_time":0.6460552267},
{"learn":[4.339329044],"iteration":343,"passed_time":0.3379940794,"remaining_time":0.644546849},
{"learn":[4.335859758],"iteration":344,"passed_time":0.3387020605,"remaining_time":0.6430430423},
{"learn":[4.334658586],"iteration":345,"passed_time":0.3394167029,"remaining_time":0.6415564269},
{"learn":[4.331110858],"iteration":346,"passed_time":0.3401119174,"remaining_time":0.6400377006},
{"learn":[4.326821678],"iteration":347,"passed_time":0.3408363527,"remaining_time":0.6385784539},
{"learn":[4.323265794],"iteration":348,"passed_time":0.3416942119,"remaining_time":0.6373722978},
{"learn":[4.320801258],"iteration":349,"passed_time":0.3423763219,"remaining_time":0.6358417408},
{"learn":[4.318614724],"iteration":350,"passed_time":0.343158522,"remaining_time":0.6345010848},
{"learn":[4.31681002],"iteration":351,"passed_time":0.3438577837,"remaining_time":0.6330109199},
{"learn":[4.316453493],"iteration":352,"passed_time":0.3445179558,"remaining_time":0.6314535904},
{"learn":[4.311715345],"iteration":353,"passed_time":0.3452128569,"remaining_time":0.629964705},
{"learn":[4.31111804],"iteration":354,"passed_time":0.3459117726,"remaining_time":0.6284875868},
{"learn":[4.307734326],"iteration":355,"passed_time":0.3470078613,"remaining_time":0.6277333222},
{"learn":[4.304301692],"iteration":356,"passed_time":0.3477369207,"remaining_time":0.6263160785},
{"learn":[4.302344285],"iteration":357,"passed_time":0.3484892814,"remaining_time":0.6249444655},
{"learn":[4.301733077],"iteration":358,"passed_time":0.3492059447,"remaining_time":0.6235125642},
{"learn":[4.29765269],"iteration":359,"passed_time":0.3498982996,"remaining_time":0.6220414214},
{"learn":[4.294091168],"iteration":360,"passed_time":0.3505629645,"remaining_time":0.6205255799},
{"learn":[4.293502608],"iteration":361,"passed_time":0.3514108036,"remaining_time":0.6193372726},
{"learn":[4.289419172],"iteration":362,"passed_time":0.3521379037,"remaining_time":0.617938966},
{"learn":[4.285651578],"iteration":363,"passed_time":0.3529211092,"remaining_time":0.6166423776},
{"learn":[4.28344457],"iteration":364,"passed_time":0.3535648797,"remaining_time":0.6151060236},
{"learn":[4.280459713],"iteration":365,"passed_time":0.3542503911,"remaining_time":0.6136468524},
{"learn":[4.27921483],"iteration":366,"passed_time":0.3561645728,"remaining_time":0.6143111025},
{"learn":[4.278012205],"iteration":367,"passed_time":0.356873467,"remaining_time":0.6128913889},
{"learn":[4.272792128],"iteration":368,"passed_time":0.3576102929,"remaining_time":0.6115232921},
{"learn":[4.270149341],"iteration":369,"passed_time":0.3583528716,"remaining_time":0.610168403},
{"learn":[4.268800748],"iteration":370,"passed_time":0.3592783064,"remaining_time":0.6091268322},
{"learn":[4.264987325],"iteration":371,"passed_time":0.3600219567,"remaining_time":0.6077790022},
{"learn":[4.263158915],"iteration":372,"passed_time":0.3607908902,"remaining_time":0.6064769119},
{"learn":[4.258128097],"iteration":373,"passed_time":0.3615019483,"remaining_time":0.6050808012},
{"learn":[4.255972591],"iteration":374,"passed_time":0.3622364517,"remaining_time":0.6037274195},
{"learn":[4.252651319],"iteration":375,"passed_time":0.3635580994,"remaining_time":0.6033517395},
{"learn":[4.252110903],"iteration":376,"passed_time":0.3642934017,"remaining_time":0.6020020936},
{"learn":[4.25004848],"iteration":377,"passed_time":0.3650285591,"remaining_time":0.6006554597},
{"learn":[4.248323559],"iteration":378,"passed_time":0.3657561502,"remaining_time":0.5992996551},
{"learn":[4.246377821],"iteration":379,"passed_time":0.3664682428,"remaining_time":0.5979218698},
{"learn":[4.242659676],"iteration":380,"passed_time":0.3671676078,"remaining_time":0.5965269008},
{"learn":[4.239993054],"iteration":381,"passed_time":0.368120131,"remaining_time":0.5955451334},
{"learn":[4.237194086],"iteration":382,"passed_time":0.3688727444,"remaining_time":0.5942414707},
{"learn":[4.232339636],"iteration":383,"passed_time":0.3696084887,"remaining_time":0.5929136173},
{"learn":[4.229163266],"iteration":384,"passed_time":0.3703425238,"remaining_time":0.5915861094},
{"learn":[4.227338662],"iteration":385,"passed_time":0.3710807691,"remaining_time":0.5902683736},
{"learn":[4.224982166],"iteration":386,"passed_time":0.372093867,"remaining_time":0.5893889934},
{"learn":[4.221093472],"iteration":387,"passed_time":0.3728756947,"remaining_time":0.588144137},
{"learn":[4.218001459],"iteration":388,"passed_time":0.3735950945,"remaining_time":0.586803606},
{"learn":[4.215853225],"iteration":389,"passed_time":0.3743111364,"remaining_time":0.5854610083},
{"learn":[4.211931625],"iteration":390,"passed_time":0.3750688731,"remaining_time":0.5841865568},
{"learn":[4.207640868],"iteration":391,"passed_time":0.3760302036,"remaining_time":0.5832305199},
{"learn":[4.204389039],"iteration":392,"passed_time":0.3768696729,"remaining_time":0.5820862378},
{"learn":[4.200934846],"iteration":393,"passed_time":0.3776032632,"remaining_time":0.5807806536},
{"learn":[4.200293479],"iteration":394,"passed_time":0.3784024319,"remaining_time":0.5795784083},
{"learn":[4.199634635],"iteration":395,"passed_time":0.3792129712,"remaining_time":0.578395542},
{"learn":[4.197655766],"iteration":396,"passed_time":0.3803001495,"remaining_time":0.5776347358},
{"learn":[4.194675275],"iteration":397,"passed_time":0.3812743136,"remaining_time":0.5767013487},
{"learn":[4.192310866],"iteration":398,"passed_time":0.3822825744,"remaining_time":0.5758191158},
{"learn":[4.190440454],"iteration":399,"passed_time":0.3831986649,"remaining_time":0.5747979973},
{"learn":[4.187661967],"iteration":400,"passed_time":0.3841325446,"remaining_time":0.5738039757},
{"learn":[4.185951983],"iteration":401,"passed_time":0.3851105775,"remaining_time":0.5728759337},
{"learn":[4.184099931],"iteration":402,"passed_time":0.3870232256,"remaining_time":0.573332173},
{"learn":[4.183411265],"iteration":403,"passed_time":0.3883338061,"remaining_time":0.5728884862},
{"learn":[4.182027278],"iteration":404,"passed_time":0.3892003675,"remaining_time":0.5717881942},
{"learn":[4.177542374],"iteration":405,"passed_time":0.3902782973,"remaining_time":0.570998297},
{"learn":[4.1746691],"iteration":406,"passed_time":0.3913740301,"remaining_time":0.5702329234},
{"learn":[4.171150747],"iteration":407,"passed_time":0.3921641487,"remaining_time":0.5690224903},
{"learn":[4.16632016],"iteration":408,"passed_time":0.3932897707,"remaining_time":0.5682989106},
{"learn":[4.162783904],"iteration":409,"passed_time":0.3940441585,"remaining_time":0.5670391549},
{"learn":[4.158669361],"iteration":410,"passed_time":0.3948752662,"remaining_time":0.5658918049},
{"learn":[4.156907476],"iteration":411,"passed_time":0.3956377022,"remaining_time":0.5646479828},
{"learn":[4.155154854],"iteration":412,"passed_time":0.3964042905,"remaining_time":0.5634123935},
{"learn":[4.154333786],"iteration":413,"passed_time":0.3970800318,"remaining_time":0.5620504798},
{"learn":[4.152075259],"iteration":414,"passed_time":0.3977551272,"remaining_time":0.5606909625},
{"learn":[4.150308382],"iteration":415,"passed_time":0.3984238784,"remaining_time":0.5593258292},
{"learn":[4.148039888],"iteration":416,"passed_time":0.39908922,"remaining_time":0.5579592692},
{"learn":[4.146053745],"iteration":417,"passed_time":0.3997226298,"remaining_time":0.5565516042},
{"learn":[4.141574196],"iteration":418,"passed_time":0.4004060479,"remaining_time":0.5552169781},
{"learn":[4.140944203],"iteration":419,"passed_time":0.4010437485,"remaining_time":0.5538223194},
{"learn":[4.138287776],"iteration":420,"passed_time":0.4017339004,"remaining_time":0.5525033928},
{"learn":[4.135005272],"iteration":421,"passed_time":0.4024004586,"remaining_time":0.5511551305},
{"learn":[4.134303685],"iteration":422,"passed_time":0.4030570681,"remaining_time":0.5497965208},
{"learn":[4.131584955],"iteration":423,"passed_time":0.4037175265,"remaining_time":0.5484464511},
{"learn":[4.130179125],"iteration":424,"passed_time":0.4043986601,"remaining_time":0.547127599},
{"learn":[4.129403767],"iteration":425,"passed_time":0.4050730517,"remaining_time":0.5458026566},
{"learn":[4.126184649],"iteration":426,"passed_time":0.4058133224,"remaining_time":0.5445691657},
{"learn":[4.123430735],"iteration":427,"passed_time":0.4065805013,"remaining_time":0.543373941},
{"learn":[4.12030938],"iteration":428,"passed_time":0.4072615996,"remaining_time":0.5420661384},
{"learn":[4.117789744],"iteration":429,"passed_time":0.4079380846,"remaining_time":0.5407551354},
{"learn":[4.113319889],"iteration":430,"passed_time":0.4086575396,"remaining_time":0.5395038052},
{"learn":[4.109719227],"iteration":431,"passed_time":0.4093106074,"remaining_time":0.5381676505},
{"learn":[4.106425851],"iteration":432,"passed_time":0.4103651355,"remaining_time":0.5373603507},
{"learn":[4.103604052],"iteration":433,"passed_time":0.4114741466,"remaining_time":0.5366229654},
{"learn":[4.100255309],"iteration":434,"passed_time":0.4122090368,"remaining_time":0.5353979443},
{"learn":[4.097082534],"iteration":435,"passed_time":0.413447104,"remaining_time":0.5348260703},
{"learn":[4.094032652],"iteration":436,"passed_time":0.4141609774,"remaining_time":0.533575813},
{"learn":[4.093267593],"iteration":437,"passed_time":0.4148265373,"remaining_time":0.5322660137},
{"learn":[4.092808069],"iteration":438,"passed_time":0.415508777,"remaining_time":0.5309804644},
{"learn":[4.091344854],"iteration":439,"passed_time":0.4162229267,"remaining_time":0.5297382703},
{"learn":[4.088705317],"iteration":440,"passed_time":0.4169801615,"remaining_time":0.5285530845},
{"learn":[4.084802499],"iteration":441,"passed_time":0.4176735064,"remaining_time":0.5272891778},
{"learn":[4.083239779],"iteration":442,"passed_time":0.4184404035,"remaining_time":0.5261203268},
{"learn":[4.080328018],"iteration":443,"passed_time":0.4191678379,"remaining_time":0.5249038691},
{"learn":[4.077589598],"iteration":444,"passed_time":0.4198795854,"remaining_time":0.5236700447},
{"learn":[4.07469218],"iteration":445,"passed_time":0.4206456637,"remaining_time":0.5225060486},
{"learn":[4.07397983],"iteration":446,"passed_time":0.4213795575,"remaining_time":0.5213040163},
{"learn":[4.072555985],"iteration":447,"passed_time":0.4223345002,"remaining_time":0.5203764377},
{"learn":[4.070192821],"iteration":448,"passed_time":0.4230592135,"remaining_time":0.5191662063},
{"learn":[4.066951866],"iteration":449,"passed_time":0.4238131521,"remaining_time":0.5179938525},
{"learn":[4.065338403],"iteration":450,"passed_time":0.424613087,"remaining_time":0.5168793454},
{"learn":[4.064549039],"iteration":451,"passed_time":0.425549648,"remaining_time":0.5159318741},
{"learn":[4.060968558],"iteration":452,"passed_time":0.4264520806,"remaining_time":0.5149432408},
{"learn":[4.058210888],"iteration":453,"passed_time":0.427404525,"remaining_time":0.5140151336},
{"learn":[4.055239312],"iteration":454,"passed_time":0.4282277286,"remaining_time":0.5129321145},
{"learn":[4.05137395],"iteration":455,"passed_time":0.4290205928,"remaining_time":0.5118140405},
{"learn":[4.048151924],"iteration":456,"passed_time":0.429887675,"remaining_time":0.5107855744},
{"learn":[4.047640519],"iteration":457,"passed_time":0.430652477,"remaining_time":0.5096367741},
{"learn":[4.043821281],"iteration":458,"passed_time":0.4314056683,"remaining_time":0.5084759619},
{"learn":[4.04171444],"iteration":459,"passed_time":0.4330606653,"remaining_time":0.5083755636},
{"learn":[4.041291976],"iteration":460,"passed_time":0.4337957628,"remaining_time":0.5071928767},
{"learn":[4.036669475],"iteration":461,"passed_time":0.4345370662,"remaining_time":0.5060193541},
{"learn":[4.035527202],"iteration":462,"passed_time":0.4352582758,"remaining_time":0.5048243933},
{"learn":[4.033587046],"iteration":463,"passed_time":0.4359840335,"remaining_time":0.5036367284},
{"learn":[4.031400561],"iteration":464,"passed_time":0.4366674262,"remaining_time":0.5024023076},
{"learn":[4.029635927],"iteration":465,"passed_time":0.4373511179,"remaining_time":0.5011705943},
{"learn":[4.025154699],"iteration":466,"passed_time":0.4380326265,"remaining_time":0.4999387365},
{"learn":[4.022267945],"iteration":467,"passed_time":0.4388106308,"remaining_time":0.4988189222},
{"learn":[4.018447113],"iteration":468,"passed_time":0.4395096099,"remaining_time":0.4976110935},
{"learn":[4.01617232],"iteration":469,"passed_time":0.4401881773,"remaining_time":0.4963824127},
{"learn":[4.015665046],"iteration":470,"passed_time":0.4408668118,"remaining_time":0.4951561432},
{"learn":[4.013926713],"iteration":471,"passed_time":0.4415369388,"remaining_time":0.4939226773},
{"learn":[4.012711544],"iteration":472,"passed_time":0.4421807193,"remaining_time":0.4926622391},
{"learn":[4.010277069],"iteration":473,"passed_time":0.4428542332,"remaining_time":0.491437398},
{"learn":[4.005690101],"iteration":474,"passed_time":0.4435866124,"remaining_time":0.4902799401},
{"learn":[4.004048005],"iteration":475,"passed_time":0.4442531697,"remaining_time":0.4890518086},
{"learn":[4.000828079],"iteration":476,"passed_time":0.4449233429,"remaining_time":0.4878299965},
{"learn":[3.999618171],"iteration":477,"passed_time":0.4455617193,"remaining_time":0.4865757688},
{"learn":[3.998829986],"iteration":478,"passed_time":0.4462330719,"remaining_time":0.4853599801},
{"learn":[3.995692484],"iteration":479,"passed_time":0.4469121104,"remaining_time":0.4841547862},
{"learn":[3.990987985],"iteration":480,"passed_time":0.447583194,"remaining_time":0.4829431968},
{"learn":[3.989590143],"iteration":481,"passed_time":0.4483287872,"remaining_time":0.4818139249},
{"learn":[3.987919494],"iteration":482,"passed_time":0.4490024424,"remaining_time":0.4806092396},
{"learn":[3.985615772],"iteration":483,"passed_time":0.4496724988,"remaining_time":0.479402912},
{"learn":[3.982222654],"iteration":484,"passed_time":0.4503555637,"remaining_time":0.4782126088},
{"learn":[3.978798324],"iteration":485,"passed_time":0.4510526831,"remaining_time":0.4770392574},
{"learn":[3.976766374],"iteration":486,"passed_time":0.451747144,"remaining_time":0.4758650613},
{"learn":[3.974663919],"iteration":487,"passed_time":0.4524133724,"remaining_time":0.4746632104},
{"learn":[3.972909517],"iteration":488,"passed_time":0.4531162139,"remaining_time":0.4735018104},
{"learn":[3.970924069],"iteration":489,"passed_time":0.4538341689,"remaining_time":0.4723580125},
{"learn":[3.969521262],"iteration":490,"passed_time":0.4545656224,"remaining_time":0.4712299426},
{"learn":[3.968978375],"iteration":491,"passed_time":0.4552407939,"remaining_time":0.4700453726},
{"learn":[3.967127987],"iteration":492,"passed_time":0.4559155995,"remaining_time":0.4688624928},
{"learn":[3.963102684],"iteration":493,"passed_time":0.4565565158,"remaining_time":0.4676469575},
{"learn":[3.958381963],"iteration":494,"passed_time":0.4572409312,"remaining_time":0.4664781217},
{"learn":[3.957186492],"iteration":495,"passed_time":0.4580037694,"remaining_time":0.465390927},
{"learn":[3.956300075],"iteration":496,"passed_time":0.4588782865,"remaining_time":0.4644180647},
{"learn":[3.953827641],"iteration":497,"passed_time":0.4598576392,"remaining_time":0.4635512748},
{"learn":[3.951777646],"iteration":498,"passed_time":0.4606385602,"remaining_time":0.4624848069},
{"learn":[3.95025014],"iteration":499,"passed_time":0.4614251769,"remaining_time":0.4614251769},
{"learn":[3.948575635],"iteration":500,"passed_time":0.4621620825,"remaining_time":0.4603171241},
{"learn":[3.946895632],"iteration":501,"passed_time":0.4628793845,"remaining_time":0.4591911025},
{"learn":[3.945297751],"iteration":502,"passed_time":0.4636553425,"remaining_time":0.4581246625},
{"learn":[3.941928134],"iteration":503,"passed_time":0.4644516796,"remaining_time":0.4570794307},
{"learn":[3.938851064],"iteration":504,"passed_time":0.4652017548,"remaining_time":0.4559898389},
{"learn":[3.937155482],"iteration":505,"passed_time":0.4659437883,"remaining_time":0.4548937379},
{"learn":[3.933625611],"iteration":506,"passed_time":0.4666565367,"remaining_time":0.4537705573},
{"learn":[3.932541224],"iteration":507,"passed_time":0.4673547132,"remaining_time":0.4526348797},
{"learn":[3.927138498],"iteration":508,"passed_time":0.4681393662,"remaining_time":0.4515843395},
{"learn":[3.926022992],"iteration":509,"passed_time":0.4688484469,"remaining_time":0.4504622333},
{"learn":[3.921850051],"iteration":510,"passed_time":0.4696109952,"remaining_time":0.4493929093},
{"learn":[3.92036738],"iteration":511,"passed_time":0.4703415185,"remaining_time":0.4482942598},
{"learn":[3.918050687],"iteration":512,"passed_time":0.471292,"remaining_time":0.4474058558},
{"learn":[3.913597872],"iteration":513,"passed_time":0.4720010473,"remaining_time":0.446288928},
{"learn":[3.910621456],"iteration":514,"passed_time":0.4728023609,"remaining_time":0.4452604758},
{"learn":[3.909479979],"iteration":515,"passed_time":0.4735989353,"remaining_time":0.4442284587},
{"learn":[3.908965929],"iteration":516,"passed_time":0.4744172529,"remaining_time":0.4432176657},
{"learn":[3.90569514],"iteration":517,"passed_time":0.4751893666,"remaining_time":0.442164623},
{"learn":[3.901038823],"iteration":518,"passed_time":0.4759319635,"remaining_time":0.4410853072},
{"learn":[3.899353562],"iteration":519,"passed_time":0.4766645538,"remaining_time":0.4399980496},
{"learn":[3.897874195],"iteration":520,"passed_time":0.4774066216,"remaining_time":0.4389208671},
{"learn":[3.89595195],"iteration":521,"passed_time":0.4781191753,"remaining_time":0.4378179421},
{"learn":[3.894848981],"iteration":522,"passed_time":0.4789273233,"remaining_time":0.4368036964},
{"learn":[3.893176826],"iteration":523,"passed_time":0.4797049018,"remaining_time":0.4357624681},
{"learn":[3.891853873],"iteration":524,"passed_time":0.4804584491,"remaining_time":0.4347005015},
{"learn":[3.888141842],"iteration":525,"passed_time":0.4811726033,"remaining_time":0.433604209},
{"learn":[3.886733054],"iteration":526,"passed_time":0.4818849259,"remaining_time":0.4325077229},
{"learn":[3.881551121],"iteration":527,"passed_time":0.4825571572,"remaining_time":0.4313768527},
{"learn":[3.876473538],"iteration":528,"passed_time":0.4832646174,"remaining_time":0.4302790828},
{"learn":[3.872982132],"iteration":529,"passed_time":0.484009448,"remaining_time":0.4292159256},
{"learn":[3.869519552],"iteration":530,"passed_time":0.4848227329,"remaining_time":0.4282144289},
{"learn":[3.867075499],"iteration":531,"passed_time":0.485573416,"remaining_time":0.4271585689},
{"learn":[3.863603956],"iteration":532,"passed_time":0.4864407908,"remaining_time":0.4262060962},
{"learn":[3.861826148],"iteration":533,"passed_time":0.4872347727,"remaining_time":0.4251898953},
{"learn":[3.860417747],"iteration":534,"passed_time":0.4879966471,"remaining_time":0.4241466185},
{"learn":[3.859097527],"iteration":535,"passed_time":0.4888119438,"remaining_time":0.4231506379},
{"learn":[3.855339422],"iteration":536,"passed_time":0.4895610834,"remaining_time":0.4220982898},
{"learn":[3.850719073],"iteration":537,"passed_time":0.4902967924,"remaining_time":0.4210355355},
{"learn":[3.84692255],"iteration":538,"passed_time":0.4911054169,"remaining_time":0.4200363584},
{"learn":[3.84511688],"iteration":539,"passed_time":0.491836345,"remaining_time":0.4189717013},
{"learn":[3.840828607],"iteration":540,"passed_time":0.4926470782,"remaining_time":0.4179759869},
{"learn":[3.839581559],"iteration":541,"passed_time":0.4934134228,"remaining_time":0.4169434458},
{"learn":[3.836503936],"iteration":542,"passed_time":0.4941940077,"remaining_time":0.4159238702},
{"learn":[3.834085667],"iteration":543,"passed_time":0.4949480233,"remaining_time":0.4148829019},
{"learn":[3.831815542],"iteration":544,"passed_time":0.4957561468,"remaining_time":0.4138881593},
{"learn":[3.831314925],"iteration":545,"passed_time":0.496580826,"remaining_time":0.4129078663},
{"learn":[3.828237619],"iteration":546,"passed_time":0.4973796187,"remaining_time":0.4119067044},
{"learn":[3.827800307],"iteration":547,"passed_time":0.4982173833,"remaining_time":0.4109384256},
{"learn":[3.824639541],"iteration":548,"passed_time":0.4991564045,"remaining_time":0.410053804},
{"learn":[3.821578864],"iteration":549,"passed_time":0.4999765256,"remaining_time":0.4090717027},
{"learn":[3.819280749],"iteration":550,"passed_time":0.500737197,"remaining_time":0.408041745},
{"learn":[3.813144967],"iteration":551,"passed_time":0.5014477135,"remaining_time":0.4069720573},
{"learn":[3.812586533],"iteration":552,"passed_time":0.502226716,"remaining_time":0.4059590272},
{"learn":[3.810153051],"iteration":553,"passed_time":0.502979294,"remaining_time":0.4049255688},
{"learn":[3.808126872],"iteration":554,"passed_time":0.5038321295,"remaining_time":0.4039735093},
{"learn":[3.807344776],"iteration":555,"passed_time":0.5046292348,"remaining_time":0.4029773026},
{"learn":[3.806586116],"iteration":556,"passed_time":0.5054030732,"remaining_time":0.401963306},
{"learn":[3.802890028],"iteration":557,"passed_time":0.5075129627,"remaining_time":0.4020084758},
{"learn":[3.798774646],"iteration":558,"passed_time":0.5086414643,"remaining_time":0.4012717097},
{"learn":[3.797618926],"iteration":559,"passed_time":0.5094900452,"remaining_time":0.4003136069},
{"learn":[3.797036411],"iteration":560,"passed_time":0.5102718212,"remaining_time":0.3993036177},
{"learn":[3.796617129],"iteration":561,"passed_time":0.5110355317,"remaining_time":0.398280361},
{"learn":[3.794830417],"iteration":562,"passed_time":0.5118143965,"remaining_time":0.3972697891},
{"learn":[3.792558579],"iteration":563,"passed_time":0.5126018494,"remaining_time":0.3962666779},
{"learn":[3.791588073],"iteration":564,"passed_time":0.5136933375,"remaining_time":0.3954984103},
{"learn":[3.790055874],"iteration":565,"passed_time":0.5144597283,"remaining_time":0.394479721},
{"learn":[3.789379095],"iteration":566,"passed_time":0.5152863259,"remaining_time":0.3935078997},
{"learn":[3.786915876],"iteration":567,"passed_time":0.516026584,"remaining_time":0.392470923},
{"learn":[3.786475199],"iteration":568,"passed_time":0.5167078507,"remaining_time":0.3913903052},
{"learn":[3.78418026],"iteration":569,"passed_time":0.5174134622,"remaining_time":0.390329454},
{"learn":[3.781688718],"iteration":570,"passed_time":0.5184262059,"remaining_time":0.3895005996},
{"learn":[3.778678686],"iteration":571,"passed_time":0.5191158098,"remaining_time":0.3884293122},
{"learn":[3.778331737],"iteration":572,"passed_time":0.5197901263,"remaining_time":0.387347965},
{"learn":[3.777443415],"iteration":573,"passed_time":0.5204820599,"remaining_time":0.3862811107},
{"learn":[3.776164072],"iteration":574,"passed_time":0.5212561936,"remaining_time":0.385276317},
{"learn":[3.772285767],"iteration":575,"passed_time":0.5221303965,"remaining_time":0.3843459863},
{"learn":[3.770084387],"iteration":576,"passed_time":0.5228366076,"remaining_time":0.383292695},
{"learn":[3.767980148],"iteration":577,"passed_time":0.5235345287,"remaining_time":0.3822345521},
{"learn":[3.76760729],"iteration":578,"passed_time":0.5242656579,"remaining_time":0.3812017996},
{"learn":[3.766917656],"iteration":579,"passed_time":0.5249910316,"remaining_time":0.3801659194},
{"learn":[3.766578325],"iteration":580,"passed_time":0.5256700709,"remaining_time":0.3790976931},
{"learn":[3.765195077],"iteration":581,"passed_time":0.5263957245,"remaining_time":0.3780642832},
{"learn":[3.762464182],"iteration":582,"passed_time":0.5270708127,"remaining_time":0.3769957614},
{"learn":[3.762149579],"iteration":583,"passed_time":0.527735984,"remaining_time":0.3759215229},
{"learn":[3.760877068],"iteration":584,"passed_time":0.5284993874,"remaining_time":0.3749183689},
{"learn":[3.758764257],"iteration":585,"passed_time":0.5293452129,"remaining_time":0.373974263},
{"learn":[3.756705242],"iteration":586,"passed_time":0.5301283504,"remaining_time":0.3729863862},
{"learn":[3.756142563],"iteration":587,"passed_time":0.5308720876,"remaining_time":0.3719715988},
{"learn":[3.751514392],"iteration":588,"passed_time":0.5316594173,"remaining_time":0.3709881503},
{"learn":[3.75018972],"iteration":589,"passed_time":0.5323915112,"remaining_time":0.3699669824},
{"learn":[3.748806947],"iteration":590,"passed_time":0.5330862864,"remaining_time":0.3689209664},
{"learn":[3.747670808],"iteration":591,"passed_time":0.5338256622,"remaining_time":0.3679068753},
{"learn":[3.745503323],"iteration":592,"passed_time":0.5345860248,"remaining_time":0.3669081148},
{"learn":[3.743491654],"iteration":593,"passed_time":0.5353950088,"remaining_time":0.3659433899},
{"learn":[3.740504423],"iteration":594,"passed_time":0.5361731254,"remaining_time":0.3649581778},
{"learn":[3.738148756],"iteration":595,"passed_time":0.5371135633,"remaining_time":0.3640836906},
{"learn":[3.733903082],"iteration":596,"passed_time":0.5380056034,"remaining_time":0.3631763119},
{"learn":[3.733569626],"iteration":597,"passed_time":0.5388833824,"remaining_time":0.3622593975},
{"learn":[3.733275797],"iteration":598,"passed_time":0.5396752973,"remaining_time":0.3612851322},
{"learn":[3.73146492],"iteration":599,"passed_time":0.5404373565,"remaining_time":0.360291571},
{"learn":[3.728771607],"iteration":600,"passed_time":0.5411895278,"remaining_time":0.3592922156},
{"learn":[3.727022391],"iteration":601,"passed_time":0.541984613,"remaining_time":0.3583220531},
{"learn":[3.724889237],"iteration":602,"passed_time":0.5428754167,"remaining_time":0.35741549},
{"learn":[3.72226187],"iteration":603,"passed_time":0.5436423012,"remaining_time":0.3564277339},
{"learn":[3.720262012],"iteration":604,"passed_time":0.5444025171,"remaining_time":0.3554363541},
{"learn":[3.719768557],"iteration":605,"passed_time":0.5451703309,"remaining_time":0.3544506772},
{"learn":[3.71741432],"iteration":606,"passed_time":0.5459629161,"remaining_time":0.3534817562},
{"learn":[3.716325052],"iteration":607,"passed_time":0.5467013634,"remaining_time":0.3524785106},
{"learn":[3.712985546],"iteration":608,"passed_time":0.5475797122,"remaining_time":0.3515659564},
{"learn":[3.71268796],"iteration":609,"passed_time":0.5482872892,"remaining_time":0.3505443325},
{"learn":[3.711218456],"iteration":610,"passed_time":0.5490207455,"remaining_time":0.3495402128},
{"learn":[3.710425271],"iteration":611,"passed_time":0.5497634954,"remaining_time":0.3485428696},
{"learn":[3.708233892],"iteration":612,"passed_time":0.5505935044,"remaining_time":0.3476014457},
{"learn":[3.707499784],"iteration":613,"passed_time":0.5514224083,"remaining_time":0.3466596899},
{"learn":[3.703107174],"iteration":614,"passed_time":0.5522099091,"remaining_time":0.3456923821},
{"learn":[3.702807873],"iteration":615,"passed_time":0.5531745785,"remaining_time":0.3448361009},
{"learn":[3.702263281],"iteration":616,"passed_time":0.5542342579,"remaining_time":0.3440384454},
{"learn":[3.701603654],"iteration":617,"passed_time":0.5549581388,"remaining_time":0.3430323771},
{"learn":[3.699283514],"iteration":618,"passed_time":0.5557589443,"remaining_time":0.3420745683},
{"learn":[3.698292224],"iteration":619,"passed_time":0.5565123158,"remaining_time":0.3410881935},
{"learn":[3.695558596],"iteration":620,"passed_time":0.5572862484,"remaining_time":0.3401151178},
{"learn":[3.692377295],"iteration":621,"passed_time":0.5580253443,"remaining_time":0.3391215115},
{"learn":[3.690389601],"iteration":622,"passed_time":0.5587802086,"remaining_time":0.3381382643},
{"learn":[3.686850518],"iteration":623,"passed_time":0.5595266533,"remaining_time":0.3371506757},
{"learn":[3.68649056],"iteration":624,"passed_time":0.5602217537,"remaining_time":0.3361330522},
{"learn":[3.685994847],"iteration":625,"passed_time":0.5609888674,"remaining_time":0.3351594831},
{"learn":[3.684659111],"iteration":626,"passed_time":0.5617702539,"remaining_time":0.3341950634},
{"learn":[3.682424982],"iteration":627,"passed_time":0.5625294154,"remaining_time":0.3332180614},
{"learn":[3.682074559],"iteration":628,"passed_time":0.5632787832,"remaining_time":0.3322359755},
{"learn":[3.680214318],"iteration":629,"passed_time":0.5642863611,"remaining_time":0.3314062756},
{"learn":[3.679099077],"iteration":630,"passed_time":0.5650560853,"remaining_time":0.3304369183},
{"learn":[3.67757957],"iteration":631,"passed_time":0.565777063,"remaining_time":0.3294398089},
{"learn":[3.674835411],"iteration":632,"passed_time":0.5665786104,"remaining_time":0.3284902844},
{"learn":[3.669676635],"iteration":633,"passed_time":0.5710825837,"remaining_time":0.3296785893},
{"learn":[3.668028055],"iteration":634,"passed_time":0.5720789294,"remaining_time":0.3288327705},
{"learn":[3.665830658],"iteration":635,"passed_time":0.5729592538,"remaining_time":0.327920076},
{"learn":[3.662962166],"iteration":636,"passed_time":0.5737932936,"remaining_time":0.3269811077},
{"learn":[3.662438867],"iteration":637,"passed_time":0.5745961462,"remaining_time":0.3260247726},
{"learn":[3.660499669],"iteration":638,"passed_time":0.575880891,"remaining_time":0.3253411606},
{"learn":[3.659976402],"iteration":639,"passed_time":0.5768866826,"remaining_time":0.324498759},
{"learn":[3.65813491],"iteration":640,"passed_time":0.577700424,"remaining_time":0.3235482874},
{"learn":[3.654196882],"iteration":641,"passed_time":0.5784877672,"remaining_time":0.3225835213},
{"learn":[3.651716238],"iteration":642,"passed_time":0.579269239,"remaining_time":0.3216160471},
{"learn":[3.650330763],"iteration":643,"passed_time":0.5800912387,"remaining_time":0.3206715543},
{"learn":[3.648871431],"iteration":644,"passed_time":0.5808866528,"remaining_time":0.3197128089},
{"learn":[3.648545479],"iteration":645,"passed_time":0.5817677652,"remaining_time":0.3188015307},
{"learn":[3.645216135],"iteration":646,"passed_time":0.5825738805,"remaining_time":0.3178494279},
{"learn":[3.64302834],"iteration":647,"passed_time":0.5833642646,"remaining_time":0.3168892301},
{"learn":[3.639439048],"iteration":648,"passed_time":0.5841191515,"remaining_time":0.3159103578},
{"learn":[3.637333262],"iteration":649,"passed_time":0.5848574783,"remaining_time":0.3149232576},
{"learn":[3.636413282],"iteration":650,"passed_time":0.5856703094,"remaining_time":0.3139768633},
{"learn":[3.635397192],"iteration":651,"passed_time":0.5864116408,"remaining_time":0.3129927163},
{"learn":[3.633256769],"iteration":652,"passed_time":0.5875365662,"remaining_time":0.3122131523},
{"learn":[3.628701107],"iteration":653,"passed_time":0.5882498246,"remaining_time":0.311214739},
{"learn":[3.627624117],"iteration":654,"passed_time":0.5890896245,"remaining_time":0.310283848},
{"learn":[3.626174768],"iteration":655,"passed_time":0.5898855784,"remaining_time":0.3093302423},
{"learn":[3.623705287],"iteration":656,"passed_time":0.5907396105,"remaining_time":0.3084074375},
{"learn":[3.622887054],"iteration":657,"passed_time":0.591490617,"remaining_time":0.3074312933},
{"learn":[3.620448393],"iteration":658,"passed_time":0.5923625389,"remaining_time":0.3065184003},
{"learn":[3.617791758],"iteration":659,"passed_time":0.5931307233,"remaining_time":0.3055521908},
{"learn":[3.617490966],"iteration":660,"passed_time":0.5942135001,"remaining_time":0.3047479222},
{"learn":[3.616360325],"iteration":661,"passed_time":0.5949592574,"remaining_time":0.3037707386},
{"learn":[3.614230412],"iteration":662,"passed_time":0.5957534957,"remaining_time":0.302818896},
{"learn":[3.612491889],"iteration":663,"passed_time":0.5966143875,"remaining_time":0.3019012563},
{"learn":[3.610470051],"iteration":664,"passed_time":0.5974888639,"remaining_time":0.3009906307},
{"learn":[3.60867093],"iteration":665,"passed_time":0.5982075617,"remaining_time":0.3000019904},
{"learn":[3.607592818],"iteration":666,"passed_time":0.5989803403,"remaining_time":0.2990411594},
{"learn":[3.605760368],"iteration":667,"passed_time":0.5997940899,"remaining_time":0.2981012542},
{"learn":[3.604420544],"iteration":668,"passed_time":0.6005272979,"remaining_time":0.2971218769},
{"learn":[3.602714004],"iteration":669,"passed_time":0.6012439169,"remaining_time":0.2961350635},
{"learn":[3.600146314],"iteration":670,"passed_time":0.6019572205,"remaining_time":0.29514743},
{"learn":[3.598359692],"iteration":671,"passed_time":0.6026641427,"remaining_time":0.2941574982},
{"learn":[3.597383333],"iteration":672,"passed_time":0.6034039986,"remaining_time":0.2931844094},
{"learn":[3.594491129],"iteration":673,"passed_time":0.6042053385,"remaining_time":0.2922417512},
{"learn":[3.593972264],"iteration":674,"passed_time":0.6049097588,"remaining_time":0.2912528468},
{"learn":[3.593210646],"iteration":675,"passed_time":0.6056009778,"remaining_time":0.2902584568},
{"learn":[3.590242902],"iteration":676,"passed_time":0.6062680359,"remaining_time":0.2892534351},
{"learn":[3.588987555],"iteration":677,"passed_time":0.6070093157,"remaining_time":0.2882846603},
{"learn":[3.587840646],"iteration":678,"passed_time":0.6078092452,"remaining_time":0.2873442824},
{"learn":[3.585436006],"iteration":679,"passed_time":0.608497138,"remaining_time":0.2863515944},
{"learn":[3.585085098],"iteration":680,"passed_time":0.6091963843,"remaining_time":0.2853651198},
{"learn":[3.583053385],"iteration":681,"passed_time":0.6098942692,"remaining_time":0.2843788528},
{"learn":[3.581824808],"iteration":682,"passed_time":0.6105737071,"remaining_time":0.2833848685},
{"learn":[3.578789193],"iteration":683,"passed_time":0.6113838932,"remaining_time":0.282452208},
{"learn":[3.57814657],"iteration":684,"passed_time":0.6121038954,"remaining_time":0.2814784337},
{"learn":[3.576567279],"iteration":685,"passed_time":0.6128011788,"remaining_time":0.2804950002},
{"learn":[3.576051112],"iteration":686,"passed_time":0.6150900222,"remaining_time":0.280237521},
{"learn":[3.57580681],"iteration":687,"passed_time":0.6159835325,"remaining_time":0.2793413694},
{"learn":[3.575567123],"iteration":688,"passed_time":0.6167740171,"remaining_time":0.2783987218},
{"learn":[3.573812195],"iteration":689,"passed_time":0.6175545259,"remaining_time":0.2774520334},
{"learn":[3.572717923],"iteration":690,"passed_time":0.6182934651,"remaining_time":0.2764872369},
{"learn":[3.569485669],"iteration":691,"passed_time":0.6189982858,"remaining_time":0.2755079076},
{"learn":[3.569068074],"iteration":692,"passed_time":0.6198329516,"remaining_time":0.274586892},
{"learn":[3.566995118],"iteration":693,"passed_time":0.6205958994,"remaining_time":0.2736345032},
{"learn":[3.564184544],"iteration":694,"passed_time":0.6213539313,"remaining_time":0.2726805022},
{"learn":[3.562562309],"iteration":695,"passed_time":0.6220684741,"remaining_time":0.2717080692},
{"learn":[3.561709341],"iteration":696,"passed_time":0.6227675954,"remaining_time":0.270729672},
{"learn":[3.560657901],"iteration":697,"passed_time":0.6235028552,"remaining_time":0.269767711},
{"learn":[3.557553589],"iteration":698,"passed_time":0.624331615,"remaining_time":0.2688466611},
{"learn":[3.554593961],"iteration":699,"passed_time":0.625043406,"remaining_time":0.2678757454},
{"learn":[3.55159375],"iteration":700,"passed_time":0.6257597912,"remaining_time":0.2669075286},
{"learn":[3.55056621],"iteration":701,"passed_time":0.6264702678,"remaining_time":0.2659375211},
{"learn":[3.549347762],"iteration":702,"passed_time":0.627234222,"remaining_time":0.2649908448},
{"learn":[3.547810525],"iteration":703,"passed_time":0.6279667081,"remaining_time":0.2640314568},
{"learn":[3.547071565],"iteration":704,"passed_time":0.6287700082,"remaining_time":0.2631023439},
{"learn":[3.545836439],"iteration":705,"passed_time":0.6295958939,"remaining_time":0.2621829926},
{"learn":[3.54383999],"iteration":706,"passed_time":0.6303741454,"remaining_time":0.2612441649},
{"learn":[3.5435204],"iteration":707,"passed_time":0.6311561416,"remaining_time":0.2603073353},
{"learn":[3.540843981],"iteration":708,"passed_time":0.6319824467,"remaining_time":0.2593891283},
{"learn":[3.538256655],"iteration":709,"passed_time":0.6327228062,"remaining_time":0.2584360758},
{"learn":[3.536477442],"iteration":710,"passed_time":0.6334995595,"remaining_time":0.2574984145},
{"learn":[3.534506908],"iteration":711,"passed_time":0.6342738228,"remaining_time":0.256560198},
{"learn":[3.531245094],"iteration":712,"passed_time":0.6351099243,"remaining_time":0.2556473328},
{"learn":[3.530045952],"iteration":713,"passed_time":0.6359235027,"remaining_time":0.2547256607},
{"learn":[3.529818611],"iteration":714,"passed_time":0.6366579372,"remaining_time":0.2537727442},
{"learn":[3.527597906],"iteration":715,"passed_time":0.6374367214,"remaining_time":0.2528380291},
{"learn":[3.525873777],"iteration":716,"passed_time":0.6382179657,"remaining_time":0.2519047201},
{"learn":[3.525389104],"iteration":717,"passed_time":0.6389636197,"remaining_time":0.2509578562},
{"learn":[3.524502527],"iteration":718,"passed_time":0.6397963987,"remaining_time":0.2500456023},
{"learn":[3.52354093],"iteration":719,"passed_time":0.6405957711,"remaining_time":0.2491205777},
{"learn":[3.521865017],"iteration":720,"passed_time":0.6413869559,"remaining_time":0.2481927333},
{"learn":[3.519662649],"iteration":721,"passed_time":0.6420873635,"remaining_time":0.2472303145},
{"learn":[3.51638953],"iteration":722,"passed_time":0.6428617835,"remaining_time":0.2462969765},
{"learn":[3.514312458],"iteration":723,"passed_time":0.6436036113,"remaining_time":0.2453516529},
{"learn":[3.513320024],"iteration":724,"passed_time":0.6443608723,"remaining_time":0.2444127447},
{"learn":[3.511326441],"iteration":725,"passed_time":0.645116666,"remaining_time":0.243473783},
{"learn":[3.508098741],"iteration":726,"passed_time":0.6462370759,"remaining_time":0.2426722445},
{"learn":[3.506116996],"iteration":727,"passed_time":0.6470531806,"remaining_time":0.2417561334},
{"learn":[3.505201665],"iteration":728,"passed_time":0.6478128031,"remaining_time":0.2408192999},
{"learn":[3.504103392],"iteration":729,"passed_time":0.6486109428,"remaining_time":0.239897198},
{"learn":[3.503607268],"iteration":730,"passed_time":0.6493329849,"remaining_time":0.2389474322},
{"learn":[3.503436724],"iteration":731,"passed_time":0.6501836908,"remaining_time":0.238045395},
{"learn":[3.501019311],"iteration":732,"passed_time":0.6509864836,"remaining_time":0.2371260452},
{"learn":[3.499811025],"iteration":733,"passed_time":0.6517278875,"remaining_time":0.2361847658},
{"learn":[3.498736433],"iteration":734,"passed_time":0.6525329603,"remaining_time":0.2352669857},
{"learn":[3.498515487],"iteration":735,"passed_time":0.6532918745,"remaining_time":0.234332955},
{"learn":[3.498015793],"iteration":736,"passed_time":0.6540361661,"remaining_time":0.2333941814},
{"learn":[3.49719449],"iteration":737,"passed_time":0.6549443723,"remaining_time":0.2325141268},
{"learn":[3.496247047],"iteration":738,"passed_time":0.6557363606,"remaining_time":0.2315929501},
{"learn":[3.49363725],"iteration":739,"passed_time":0.6565201539,"remaining_time":0.2306692433},
{"learn":[3.490947765],"iteration":740,"passed_time":0.6572688143,"remaining_time":0.2297336342},
{"learn":[3.489527783],"iteration":741,"passed_time":0.6580182754,"remaining_time":0.2287988074},
{"learn":[3.486857851],"iteration":742,"passed_time":0.6588957944,"remaining_time":0.2279087741},
{"learn":[3.486151469],"iteration":743,"passed_time":0.6596654887,"remaining_time":0.2269816735},
{"learn":[3.484974806],"iteration":744,"passed_time":0.6604375083,"remaining_time":0.2260557914},
{"learn":[3.483614277],"iteration":745,"passed_time":0.6611826369,"remaining_time":0.2251211659},
{"learn":[3.482715308],"iteration":746,"passed_time":0.6619416254,"remaining_time":0.2241917419},
{"learn":[3.479904821],"iteration":747,"passed_time":0.6626601746,"remaining_time":0.2232491497},
{"learn":[3.477125893],"iteration":748,"passed_time":0.6637978285,"remaining_time":0.2224476034},
{"learn":[3.475967227],"iteration":749,"passed_time":0.6645589611,"remaining_time":0.2215196537},
{"learn":[3.47495961],"iteration":750,"passed_time":0.665434451,"remaining_time":0.2206300643},
{"learn":[3.472705443],"iteration":751,"passed_time":0.6662576474,"remaining_time":0.2197232667},
{"learn":[3.472222906],"iteration":752,"passed_time":0.6671582248,"remaining_time":0.2188420737},
{"learn":[3.469680457],"iteration":753,"passed_time":0.668252559,"remaining_time":0.2180240444},
{"learn":[3.467954818],"iteration":754,"passed_time":0.669672514,"remaining_time":0.2173109483},
{"learn":[3.466751009],"iteration":755,"passed_time":0.6704977964,"remaining_time":0.2164040507},
{"learn":[3.464965171],"iteration":756,"passed_time":0.6714982382,"remaining_time":0.2155535956},
{"learn":[3.463733245],"iteration":757,"passed_time":0.6721850169,"remaining_time":0.2146026043},
{"learn":[3.46079457],"iteration":758,"passed_time":0.6731541773,"remaining_time":0.213741972},
{"learn":[3.460265136],"iteration":759,"passed_time":0.673906826,"remaining_time":0.2128126819},
{"learn":[3.457600153],"iteration":760,"passed_time":0.6760987652,"remaining_time":0.2123358803},
{"learn":[3.455547809],"iteration":761,"passed_time":0.6770242281,"remaining_time":0.2114590109},
{"learn":[3.453433406],"iteration":762,"passed_time":0.6777843163,"remaining_time":0.2105306461},
{"learn":[3.452429212],"iteration":763,"passed_time":0.6785492424,"remaining_time":0.2096042162},
{"learn":[3.450721827],"iteration":764,"passed_time":0.6792759612,"remaining_time":0.2086664717},
{"learn":[3.449995134],"iteration":765,"passed_time":0.680042967,"remaining_time":0.2077415852},
{"learn":[3.447566464],"iteration":766,"passed_time":0.6808226434,"remaining_time":0.2068209595},
{"learn":[3.445354533],"iteration":767,"passed_time":0.6816769772,"remaining_time":0.2059232535},
{"learn":[3.445009339],"iteration":768,"passed_time":0.6825863809,"remaining_time":0.2050422028},
{"learn":[3.442757961],"iteration":769,"passed_time":0.6833950534,"remaining_time":0.20413099},
{"learn":[3.441894031],"iteration":770,"passed_time":0.6842288976,"remaining_time":0.2032275195},
{"learn":[3.440392913],"iteration":771,"passed_time":0.6849642651,"remaining_time":0.2022951457},
{"learn":[3.438418123],"iteration":772,"passed_time":0.685746543,"remaining_time":0.2013770573},
{"learn":[3.43618504],"iteration":773,"passed_time":0.6864657336,"remaining_time":0.2004408989},
{"learn":[3.434772231],"iteration":774,"passed_time":0.6879018193,"remaining_time":0.1997134314},
{"learn":[3.434564263],"iteration":775,"passed_time":0.6886312891,"remaining_time":0.1987801659},
{"learn":[3.434253745],"iteration":776,"passed_time":0.6893537642,"remaining_time":0.1978454175},
{"learn":[3.433134319],"iteration":777,"passed_time":0.6900791324,"remaining_time":0.1969120403},
{"learn":[3.432212465],"iteration":778,"passed_time":0.6907489297,"remaining_time":0.1959634319},
{"learn":[3.430450106],"iteration":779,"passed_time":0.6915343843,"remaining_time":0.1950481597},
{"learn":[3.428861984],"iteration":780,"passed_time":0.6922842168,"remaining_time":0.1941232311},
{"learn":[3.427026777],"iteration":781,"passed_time":0.6930961747,"remaining_time":0.1932160692},
{"learn":[3.426784128],"iteration":782,"passed_time":0.6938478559,"remaining_time":0.1922924454},
{"learn":[3.426071593],"iteration":783,"passed_time":0.6945184241,"remaining_time":0.1913469128},
{"learn":[3.42538167],"iteration":784,"passed_time":0.6954096481,"remaining_time":0.1904625151},
{"learn":[3.424250658],"iteration":785,"passed_time":0.6961869169,"remaining_time":0.1895470741},
{"learn":[3.42247578],"iteration":786,"passed_time":0.6973817296,"remaining_time":0.1887449916},
{"learn":[3.42158724],"iteration":787,"passed_time":0.6980365981,"remaining_time":0.1877966482},
{"learn":[3.419669333],"iteration":788,"passed_time":0.6986892982,"remaining_time":0.1868484688},
{"learn":[3.418345126],"iteration":789,"passed_time":0.6995209539,"remaining_time":0.185948608},
{"learn":[3.416782184],"iteration":790,"passed_time":0.7002319432,"remaining_time":0.1850170368},
{"learn":[3.415961739],"iteration":791,"passed_time":0.7008908762,"remaining_time":0.1840723513},
{"learn":[3.41415017],"iteration":792,"passed_time":0.7015191356,"remaining_time":0.1831203796},
{"learn":[3.411801715],"iteration":793,"passed_time":0.7021893052,"remaining_time":0.1821800968},
{"learn":[3.41060679],"iteration":794,"passed_time":0.7028650981,"remaining_time":0.1812419435},
{"learn":[3.409897059],"iteration":795,"passed_time":0.7036630765,"remaining_time":0.1803357633},
{"learn":[3.409592338],"iteration":796,"passed_time":0.7043477328,"remaining_time":0.1794009909},
{"learn":[3.409033038],"iteration":797,"passed_time":0.7050277541,"remaining_time":0.1784656721},
{"learn":[3.407516419],"iteration":798,"passed_time":0.705797154,"remaining_time":0.1775534768},
{"learn":[3.406580444],"iteration":799,"passed_time":0.7064981078,"remaining_time":0.176624527},
{"learn":[3.403860244],"iteration":800,"passed_time":0.7073114298,"remaining_time":0.1757240631},
{"learn":[3.40366991],"iteration":801,"passed_time":0.7079725594,"remaining_time":0.1747862428},
{"learn":[3.402240672],"iteration":802,"passed_time":0.7086291871,"remaining_time":0.1738480073},
{"learn":[3.400115895],"iteration":803,"passed_time":0.712100313,"remaining_time":0.1735965937},
{"learn":[3.39836159],"iteration":804,"passed_time":0.7132893774,"remaining_time":0.1727843834},
{"learn":[3.39757913],"iteration":805,"passed_time":0.714437902,"remaining_time":0.1719614801},
{"learn":[3.395136783],"iteration":806,"passed_time":0.7154668091,"remaining_time":0.1711091625},
{"learn":[3.393526596],"iteration":807,"passed_time":0.7162570147,"remaining_time":0.1701996867},
{"learn":[3.392941576],"iteration":808,"passed_time":0.7169679307,"remaining_time":0.1692717859},
{"learn":[3.391079964],"iteration":809,"passed_time":0.7179469083,"remaining_time":0.1684072995},
{"learn":[3.388284075],"iteration":810,"passed_time":0.718647853,"remaining_time":0.1674777364},
{"learn":[3.38797394],"iteration":811,"passed_time":0.7194125246,"remaining_time":0.1665634909},
{"learn":[3.387513691],"iteration":812,"passed_time":0.7200879262,"remaining_time":0.1656290802},
{"learn":[3.38537997],"iteration":813,"passed_time":0.7207897187,"remaining_time":0.1647013362},
{"learn":[3.384343326],"iteration":814,"passed_time":0.7214927821,"remaining_time":0.1637744352},
{"learn":[3.382538123],"iteration":815,"passed_time":0.7223998769,"remaining_time":0.1628940899},
{"learn":[3.382115714],"iteration":816,"passed_time":0.7231153555,"remaining_time":0.1619707589},
{"learn":[3.380890969],"iteration":817,"passed_time":0.7239064759,"remaining_time":0.161064766},
{"learn":[3.37997406],"iteration":818,"passed_time":0.724689714,"remaining_time":0.1601573116},
{"learn":[3.377693199],"iteration":819,"passed_time":0.7254217644,"remaining_time":0.1592389239},
{"learn":[3.374059849],"iteration":820,"passed_time":0.726379469,"remaining_time":0.1583701887},
{"learn":[3.372039604],"iteration":821,"passed_time":0.7271177016,"remaining_time":0.1574537115},
{"learn":[3.36972979],"iteration":822,"passed_time":0.7278450092,"remaining_time":0.1565353179},
{"learn":[3.367531088],"iteration":823,"passed_time":0.728575728,"remaining_time":0.1556181167},
{"learn":[3.367320363],"iteration":824,"passed_time":0.7292634777,"remaining_time":0.1546922529},
{"learn":[3.365447446],"iteration":825,"passed_time":0.7300048101,"remaining_time":0.153778253},
{"learn":[3.365201925],"iteration":826,"passed_time":0.7311794747,"remaining_time":0.1529553194},
{"learn":[3.364131024],"iteration":827,"passed_time":0.7319596457,"remaining_time":0.1520495882},
{"learn":[3.363689946],"iteration":828,"passed_time":0.7327668217,"remaining_time":0.1511497304},
{"learn":[3.361859856],"iteration":829,"passed_time":0.7334360076,"remaining_time":0.1502218329},
{"learn":[3.361274448],"iteration":830,"passed_time":0.7341089192,"remaining_time":0.1492953157},
{"learn":[3.359195693],"iteration":831,"passed_time":0.7349670655,"remaining_time":0.1484068113},
{"learn":[3.355412618],"iteration":832,"passed_time":0.7356704324,"remaining_time":0.1474873496},
{"learn":[3.351987736],"iteration":833,"passed_time":0.7363940777,"remaining_time":0.1465724423},
{"learn":[3.351177182],"iteration":834,"passed_time":0.7371722831,"remaining_time":0.1456687745},
{"learn":[3.350251301],"iteration":835,"passed_time":0.7378626787,"remaining_time":0.144748181},
{"learn":[3.34848283],"iteration":836,"passed_time":0.7385320928,"remaining_time":0.1438240515},
{"learn":[3.347226863],"iteration":837,"passed_time":0.7394661338,"remaining_time":0.142951687},
{"learn":[3.346859007],"iteration":838,"passed_time":0.7402105468,"remaining_time":0.1420427867},
{"learn":[3.345360461],"iteration":839,"passed_time":0.740971895,"remaining_time":0.1411375038},
{"learn":[3.342307545],"iteration":840,"passed_time":0.7416462938,"remaining_time":0.1402161245},
{"learn":[3.34017651],"iteration":841,"passed_time":0.7423569951,"remaining_time":0.139302144},
{"learn":[3.339047821],"iteration":842,"passed_time":0.7431872269,"remaining_time":0.138410907},
{"learn":[3.336704987],"iteration":843,"passed_time":0.7439465623,"remaining_time":0.1375067106},
{"learn":[3.334763617],"iteration":844,"passed_time":0.7446349026,"remaining_time":0.1365898342},
{"learn":[3.333569472],"iteration":845,"passed_time":0.745438469,"remaining_time":0.1356944731},
{"learn":[3.331341549],"iteration":846,"passed_time":0.7461235257,"remaining_time":0.1347779214},
{"learn":[3.330731539],"iteration":847,"passed_time":0.7469623745,"remaining_time":0.1338894822},
{"learn":[3.328715337],"iteration":848,"passed_time":0.7477154779,"remaining_time":0.1329859095},
{"learn":[3.328310637],"iteration":849,"passed_time":0.7487958643,"remaining_time":0.1321404466},
{"learn":[3.326644684],"iteration":850,"passed_time":0.749576519,"remaining_time":0.1312419522},
{"learn":[3.32623682],"iteration":851,"passed_time":0.7506768986,"remaining_time":0.1303992735},
{"learn":[3.324783739],"iteration":852,"passed_time":0.7514665281,"remaining_time":0.129502438},
{"learn":[3.322395406],"iteration":853,"passed_time":0.7522146223,"remaining_time":0.1285987528},
{"learn":[3.320891503],"iteration":854,"passed_time":0.7528910756,"remaining_time":0.1276832818},
{"learn":[3.319929779],"iteration":855,"passed_time":0.7535813235,"remaining_time":0.1267706899},
{"learn":[3.317242718],"iteration":856,"passed_time":0.7542714057,"remaining_time":0.1258585893},
{"learn":[3.315508767],"iteration":857,"passed_time":0.7551267023,"remaining_time":0.1249743493},
{"learn":[3.312807226],"iteration":858,"passed_time":0.7558678535,"remaining_time":0.1240714404},
{"learn":[3.310746345],"iteration":859,"passed_time":0.7565626595,"remaining_time":0.1231613632},
{"learn":[3.308358465],"iteration":860,"passed_time":0.7572994337,"remaining_time":0.1222585613},
{"learn":[3.306654851],"iteration":861,"passed_time":0.7580165056,"remaining_time":0.1213529905},
{"learn":[3.305451805],"iteration":862,"passed_time":0.7587201234,"remaining_time":0.1204457206},
{"learn":[3.304620601],"iteration":863,"passed_time":0.7594073006,"remaining_time":0.1195363344},
{"learn":[3.303593673],"iteration":864,"passed_time":0.7603068173,"remaining_time":0.1186606015},
{"learn":[3.301588926],"iteration":865,"passed_time":0.7614991653,"remaining_time":0.1178301249},
{"learn":[3.301368764],"iteration":866,"passed_time":0.7621796875,"remaining_time":0.1169202981},
{"learn":[3.300963099],"iteration":867,"passed_time":0.7628402953,"remaining_time":0.1160079712},
{"learn":[3.300326096],"iteration":868,"passed_time":0.7635776402,"remaining_time":0.1151077916},
{"learn":[3.299525666],"iteration":869,"passed_time":0.7643896271,"remaining_time":0.1142191397},
{"learn":[3.298090629],"iteration":870,"passed_time":0.7651167309,"remaining_time":0.1133180922},
{"learn":[3.295291082],"iteration":871,"passed_time":0.7658545042,"remaining_time":0.1124190098},
{"learn":[3.294888894],"iteration":872,"passed_time":0.7665380183,"remaining_time":0.1115124036},
{"learn":[3.293265322],"iteration":873,"passed_time":0.767302775,"remaining_time":0.1106180202},
{"learn":[3.292968158],"iteration":874,"passed_time":0.768160983,"remaining_time":0.1097372833},
{"learn":[3.290664761],"iteration":875,"passed_time":0.7690151845,"remaining_time":0.1088560307},
{"learn":[3.288366489],"iteration":876,"passed_time":0.7697205894,"remaining_time":0.1079539709},
{"learn":[3.284163257],"iteration":877,"passed_time":0.7705609129,"remaining_time":0.1070711063},
{"learn":[3.28196226],"iteration":878,"passed_time":0.7713359008,"remaining_time":0.1061793447},
{"learn":[3.281168657],"iteration":879,"passed_time":0.7722212361,"remaining_time":0.1053028958},
{"learn":[3.279310047],"iteration":880,"passed_time":0.7730731332,"remaining_time":0.1044219102},
{"learn":[3.278170822],"iteration":881,"passed_time":0.7737803072,"remaining_time":0.1035216284},
{"learn":[3.276503007],"iteration":882,"passed_time":0.774483213,"remaining_time":0.1026212185},
{"learn":[3.2751265],"iteration":883,"passed_time":0.7753843213,"remaining_time":0.1017472639},
{"learn":[3.274114527],"iteration":884,"passed_time":0.7761488108,"remaining_time":0.1008554952},
{"learn":[3.273691453],"iteration":885,"passed_time":0.7768533488,"remaining_time":0.09995629996},
{"learn":[3.273520421],"iteration":886,"passed_time":0.7775113724,"remaining_time":0.0990516179},
{"learn":[3.272880663],"iteration":887,"passed_time":0.7781682229,"remaining_time":0.09814734343},
{"learn":[3.271193282],"iteration":888,"passed_time":0.7788692446,"remaining_time":0.09724914078},
{"learn":[3.269349823],"iteration":889,"passed_time":0.7795421108,"remaining_time":0.09634790134},
{"learn":[3.268543785],"iteration":890,"passed_time":0.7802071064,"remaining_time":0.09544621167},
{"learn":[3.268338064],"iteration":891,"passed_time":0.7809319248,"remaining_time":0.09455229583},
{"learn":[3.267725988],"iteration":892,"passed_time":0.781789659,"remaining_time":0.09367468478},
{"learn":[3.266978206],"iteration":893,"passed_time":0.7825513178,"remaining_time":0.09278572672},
{"learn":[3.264899811],"iteration":894,"passed_time":0.7832951004,"remaining_time":0.09189495591},
{"learn":[3.264608725],"iteration":895,"passed_time":0.7842582226,"remaining_time":0.09102997227},
{"learn":[3.261905606],"iteration":896,"passed_time":0.7850218452,"remaining_time":0.09014186183},
{"learn":[3.260220917],"iteration":897,"passed_time":0.7858565028,"remaining_time":0.0892620972},
{"learn":[3.258640708],"iteration":898,"passed_time":0.7866234734,"remaining_time":0.08837482849},
{"learn":[3.257786813],"iteration":899,"passed_time":0.7873042854,"remaining_time":0.08747825394},
{"learn":[3.254803963],"iteration":900,"passed_time":0.7879956357,"remaining_time":0.08658331625},
{"learn":[3.254767113],"iteration":901,"passed_time":0.7887648011,"remaining_time":0.08569728437},
{"learn":[3.253388379],"iteration":902,"passed_time":0.7894723881,"remaining_time":0.08480489662},
{"learn":[3.253246169],"iteration":903,"passed_time":0.7902178301,"remaining_time":0.08391693771},
{"learn":[3.251523606],"iteration":904,"passed_time":0.7910186501,"remaining_time":0.08303510691},
{"learn":[3.251469113],"iteration":905,"passed_time":0.7915145788,"remaining_time":0.08212182164},
{"learn":[3.250863255],"iteration":906,"passed_time":0.7924508698,"remaining_time":0.08125460959},
{"learn":[3.250292235],"iteration":907,"passed_time":0.7931275867,"remaining_time":0.08036094491},
{"learn":[3.248194228],"iteration":908,"passed_time":0.7938063525,"remaining_time":0.07946796268},
{"learn":[3.247129215],"iteration":909,"passed_time":0.7945084159,"remaining_time":0.07857775542},
{"learn":[3.246889845],"iteration":910,"passed_time":0.7956425978,"remaining_time":0.07773017695},
{"learn":[3.24542371],"iteration":911,"passed_time":0.7975966272,"remaining_time":0.07696107807},
{"learn":[3.245209208],"iteration":912,"passed_time":0.7986070611,"remaining_time":0.07609946804},
{"learn":[3.243671358],"iteration":913,"passed_time":0.7993750824,"remaining_time":0.07521472329},
{"learn":[3.241286346],"iteration":914,"passed_time":0.8002385341,"remaining_time":0.0743390988},
{"learn":[3.239574456],"iteration":915,"passed_time":0.8028746156,"remaining_time":0.07362605646},
{"learn":[3.238834894],"iteration":916,"passed_time":0.8036454948,"remaining_time":0.07273999571},
{"learn":[3.235217692],"iteration":917,"passed_time":0.8048891255,"remaining_time":0.07189641426},
{"learn":[3.235008615],"iteration":918,"passed_time":0.8056079247,"remaining_time":0.07100570392},
{"learn":[3.234022342],"iteration":919,"passed_time":0.806389209,"remaining_time":0.07012080078},
{"learn":[3.230076387],"iteration":920,"passed_time":0.8070985859,"remaining_time":0.06922995471},
{"learn":[3.229177918],"iteration":921,"passed_time":0.8078650075,"remaining_time":0.06834432819},
{"learn":[3.228210267],"iteration":922,"passed_time":0.8089742116,"remaining_time":0.06748755611},
{"learn":[3.227411804],"iteration":923,"passed_time":0.8097738657,"remaining_time":0.06660477684},
{"learn":[3.226191794],"iteration":924,"passed_time":0.8104836304,"remaining_time":0.06571488895},
{"learn":[3.224960566],"iteration":925,"passed_time":0.8113328653,"remaining_time":0.06483653567},
{"learn":[3.223459237],"iteration":926,"passed_time":0.8121579973,"remaining_time":0.06395634715},
{"learn":[3.220503109],"iteration":927,"passed_time":0.8133635557,"remaining_time":0.06310579312},
{"learn":[3.218786294],"iteration":928,"passed_time":0.8141547342,"remaining_time":0.0622228053},
{"learn":[3.217861531],"iteration":929,"passed_time":0.8163724647,"remaining_time":0.06144738982},
{"learn":[3.217530126],"iteration":930,"passed_time":0.8173012221,"remaining_time":0.06057334514},
{"learn":[3.216511762],"iteration":931,"passed_time":0.8180497285,"remaining_time":0.05968603169},
{"learn":[3.213181984],"iteration":932,"passed_time":0.8188093103,"remaining_time":0.05879981113},
{"learn":[3.212969341],"iteration":933,"passed_time":0.8195294293,"remaining_time":0.05791107316},
{"learn":[3.210845399],"iteration":934,"passed_time":0.8203121085,"remaining_time":0.05702704497},
{"learn":[3.208026659],"iteration":935,"passed_time":0.8212314417,"remaining_time":0.05615257721},
{"learn":[3.20705213],"iteration":936,"passed_time":0.8219684307,"remaining_time":0.05526575361},
{"learn":[3.205695949],"iteration":937,"passed_time":0.8227816295,"remaining_time":0.05438428681},
{"learn":[3.204132437],"iteration":938,"passed_time":0.8235538547,"remaining_time":0.05350030366},
{"learn":[3.202752936],"iteration":939,"passed_time":0.8242880329,"remaining_time":0.05261412976},
{"learn":[3.200242079],"iteration":940,"passed_time":0.8250480549,"remaining_time":0.0517298993},
{"learn":[3.198891204],"iteration":941,"passed_time":0.8260090865,"remaining_time":0.05085830893},
{"learn":[3.198409631],"iteration":942,"passed_time":0.8267785706,"remaining_time":0.04997495072},
{"learn":[3.195440745],"iteration":943,"passed_time":0.8275015502,"remaining_time":0.04908907501},
{"learn":[3.193810621],"iteration":944,"passed_time":0.8285740262,"remaining_time":0.04822388512},
{"learn":[3.192133528],"iteration":945,"passed_time":0.8293517315,"remaining_time":0.04734143076},
{"learn":[3.191805358],"iteration":946,"passed_time":0.8302947428,"remaining_time":0.04646844918},
{"learn":[3.190293173],"iteration":947,"passed_time":0.8310812817,"remaining_time":0.04558673697},
{"learn":[3.190121889],"iteration":948,"passed_time":0.8317978898,"remaining_time":0.04470146721},
{"learn":[3.188444027],"iteration":949,"passed_time":0.8325846333,"remaining_time":0.04382024386},
{"learn":[3.185409769],"iteration":950,"passed_time":0.8333218496,"remaining_time":0.04293666733},
{"learn":[3.18356835],"iteration":951,"passed_time":0.8341915451,"remaining_time":0.0420600779},
{"learn":[3.18320894],"iteration":952,"passed_time":0.8351168124,"remaining_time":0.04118624363},
{"learn":[3.181577773],"iteration":953,"passed_time":0.8359039708,"remaining_time":0.0403056422},
{"learn":[3.179180777],"iteration":954,"passed_time":0.8371448461,"remaining_time":0.03944661578},
{"learn":[3.177684052],"iteration":955,"passed_time":0.8380692909,"remaining_time":0.03857222678},
{"learn":[3.177299265],"iteration":956,"passed_time":0.8388901004,"remaining_time":0.03769307661},
{"learn":[3.176223257],"iteration":957,"passed_time":0.8396089576,"remaining_time":0.03680957852},
{"learn":[3.173338127],"iteration":958,"passed_time":0.8404135349,"remaining_time":0.03593008856},
{"learn":[3.170239467],"iteration":959,"passed_time":0.8412020946,"remaining_time":0.03505008728},
{"learn":[3.169146273],"iteration":960,"passed_time":0.8419373244,"remaining_time":0.03416811202},
{"learn":[3.167328049],"iteration":961,"passed_time":0.8427375556,"remaining_time":0.03328900947},
{"learn":[3.166498279],"iteration":962,"passed_time":0.8434860421,"remaining_time":0.03240808261},
{"learn":[3.163404136],"iteration":963,"passed_time":0.8442213906,"remaining_time":0.0315269399},
{"learn":[3.162039685],"iteration":964,"passed_time":0.8449568315,"remaining_time":0.0306461027},
{"learn":[3.159880223],"iteration":965,"passed_time":0.845721609,"remaining_time":0.02976659908},
{"learn":[3.157950803],"iteration":966,"passed_time":0.846577585,"remaining_time":0.02889044499},
{"learn":[3.154801259],"iteration":967,"passed_time":0.8474061818,"remaining_time":0.0280134275},
{"learn":[3.154048259],"iteration":968,"passed_time":0.848361197,"remaining_time":0.02714055429},
{"learn":[3.153036487],"iteration":969,"passed_time":0.8493626678,"remaining_time":0.02626894849},
{"learn":[3.151810904],"iteration":970,"passed_time":0.8503079509,"remaining_time":0.02539539709},
{"learn":[3.151506761],"iteration":971,"passed_time":0.8512706392,"remaining_time":0.02452219948},
{"learn":[3.149624379],"iteration":972,"passed_time":0.8520231375,"remaining_time":0.02364298532},
{"learn":[3.148172737],"iteration":973,"passed_time":0.8528614728,"remaining_time":0.02276632268},
{"learn":[3.148015792],"iteration":974,"passed_time":0.8536230763,"remaining_time":0.02188777119},
{"learn":[3.146599731],"iteration":975,"passed_time":0.8544205049,"remaining_time":0.02101034029},
{"learn":[3.146094701],"iteration":976,"passed_time":0.855709152,"remaining_time":0.02014463715},
{"learn":[3.144831165],"iteration":977,"passed_time":0.8564655426,"remaining_time":0.01926609605},
{"learn":[3.140651292],"iteration":978,"passed_time":0.8571445358,"remaining_time":0.01838614428},
{"learn":[3.13673175],"iteration":979,"passed_time":0.8578941807,"remaining_time":0.01750804451},
{"learn":[3.136629162],"iteration":980,"passed_time":0.858824526,"remaining_time":0.01663370642},
{"learn":[3.134927218],"iteration":981,"passed_time":0.860265698,"remaining_time":0.01576861768},
{"learn":[3.133277568],"iteration":982,"passed_time":0.8609700621,"remaining_time":0.0148896145},
{"learn":[3.132660178],"iteration":983,"passed_time":0.8622068304,"remaining_time":0.01401962326},
{"learn":[3.132031005],"iteration":984,"passed_time":0.8629975822,"remaining_time":0.01314209516},
{"learn":[3.130957095],"iteration":985,"passed_time":0.8637217937,"remaining_time":0.01226379829},
{"learn":[3.128916633],"iteration":986,"passed_time":0.8644191315,"remaining_time":0.01138545968},
{"learn":[3.127838541],"iteration":987,"passed_time":0.8651621024,"remaining_time":0.01050804173},
{"learn":[3.127512818],"iteration":988,"passed_time":0.8659162457,"remaining_time":0.009631019921},
{"learn":[3.126747671],"iteration":989,"passed_time":0.8666781183,"remaining_time":0.008754324427},
{"learn":[3.125850627],"iteration":990,"passed_time":0.8674335541,"remaining_time":0.007877802207},
{"learn":[3.123276598],"iteration":991,"passed_time":0.8685489377,"remaining_time":0.007004426917},
{"learn":[3.121624234],"iteration":992,"passed_time":0.870530147,"remaining_time":0.006136667703},
{"learn":[3.1211331],"iteration":993,"passed_time":0.8712524644,"remaining_time":0.005259069202},
{"learn":[3.120941483],"iteration":994,"passed_time":0.8722392275,"remaining_time":0.004383111696},
{"learn":[3.118959423],"iteration":995,"passed_time":0.8733064461,"remaining_time":0.003507254804},
{"learn":[3.118550456],"iteration":996,"passed_time":0.8740901887,"remaining_time":0.002630161049},
{"learn":[3.117019976],"iteration":997,"passed_time":0.8748793273,"remaining_time":0.001753265185},
{"learn":[3.115818984],"iteration":998,"passed_time":0.8756624702,"remaining_time":0.0008765390093},
{"learn":[3.113717056],"iteration":999,"passed_time":0.8764371266,"remaining_time":0}
]}